package com.airpush.android;

import android.content.Context;
import org.json.JSONObject;

class FormatAds
  implements IConstants
{
  private String adType;
  private Context context;
  private long nextMessageCheckValue;

  public FormatAds(Context paramContext)
  {
    this.context = paramContext;
  }

  // ERROR //
  private void getAds(JSONObject paramJSONObject)
  {
    // Byte code:
    //   0: aload_1
    //   1: ldc 25
    //   3: invokevirtual 31	org/json/JSONObject:isNull	(Ljava/lang/String;)Z
    //   6: ifeq +332 -> 338
    //   9: ldc 33
    //   11: astore 8
    //   13: aload_1
    //   14: ldc 35
    //   16: invokevirtual 31	org/json/JSONObject:isNull	(Ljava/lang/String;)Z
    //   19: ifeq +330 -> 349
    //   22: ldc 37
    //   24: astore 9
    //   26: aload_1
    //   27: ldc 39
    //   29: invokevirtual 31	org/json/JSONObject:isNull	(Ljava/lang/String;)Z
    //   32: ifeq +328 -> 360
    //   35: ldc 41
    //   37: astore 10
    //   39: aload_1
    //   40: ldc 43
    //   42: invokevirtual 31	org/json/JSONObject:isNull	(Ljava/lang/String;)Z
    //   45: ifeq +326 -> 371
    //   48: ldc 41
    //   50: astore 11
    //   52: aload 8
    //   54: invokestatic 49	com/airpush/android/Util:setNotification_title	(Ljava/lang/String;)V
    //   57: aload 9
    //   59: invokestatic 52	com/airpush/android/Util:setNotification_text	(Ljava/lang/String;)V
    //   62: aload 11
    //   64: invokestatic 55	com/airpush/android/Util:setCampId	(Ljava/lang/String;)V
    //   67: aload 10
    //   69: invokestatic 58	com/airpush/android/Util:setCreativeId	(Ljava/lang/String;)V
    //   72: aload_0
    //   73: getfield 60	com/airpush/android/FormatAds:adType	Ljava/lang/String;
    //   76: ldc 62
    //   78: invokevirtual 68	java/lang/String:equals	(Ljava/lang/Object;)Z
    //   81: ifne +15 -> 96
    //   84: aload_0
    //   85: getfield 60	com/airpush/android/FormatAds:adType	Ljava/lang/String;
    //   88: ldc 70
    //   90: invokevirtual 68	java/lang/String:equals	(Ljava/lang/Object;)Z
    //   93: ifeq +311 -> 404
    //   96: aload_1
    //   97: ldc 72
    //   99: invokevirtual 31	org/json/JSONObject:isNull	(Ljava/lang/String;)Z
    //   102: ifeq +280 -> 382
    //   105: ldc 74
    //   107: astore 12
    //   109: aload_1
    //   110: ldc 76
    //   112: invokevirtual 31	org/json/JSONObject:isNull	(Ljava/lang/String;)Z
    //   115: ifeq +278 -> 393
    //   118: ldc 78
    //   120: astore 13
    //   122: aload 12
    //   124: invokestatic 81	com/airpush/android/Util:setNotificationUrl	(Ljava/lang/String;)V
    //   127: aload 13
    //   129: invokestatic 84	com/airpush/android/Util:setHeader	(Ljava/lang/String;)V
    //   132: aload_1
    //   133: ldc 86
    //   135: invokevirtual 31	org/json/JSONObject:isNull	(Ljava/lang/String;)Z
    //   138: ifeq +578 -> 716
    //   141: ldc 88
    //   143: astore 14
    //   145: aload_1
    //   146: ldc 90
    //   148: invokevirtual 31	org/json/JSONObject:isNull	(Ljava/lang/String;)Z
    //   151: ifeq +576 -> 727
    //   154: ldc 92
    //   156: invokestatic 98	java/lang/Long:parseLong	(Ljava/lang/String;)J
    //   159: lstore 15
    //   161: lload 15
    //   163: invokestatic 102	java/lang/Long:valueOf	(J)Ljava/lang/Long;
    //   166: astore 17
    //   168: aload_1
    //   169: ldc 104
    //   171: invokevirtual 31	org/json/JSONObject:isNull	(Ljava/lang/String;)Z
    //   174: ifeq +564 -> 738
    //   177: ldc 106
    //   179: astore 18
    //   181: aload_1
    //   182: ldc 108
    //   184: invokevirtual 31	org/json/JSONObject:isNull	(Ljava/lang/String;)Z
    //   187: ifeq +562 -> 749
    //   190: ldc 110
    //   192: astore 19
    //   194: aload_1
    //   195: ldc 112
    //   197: invokevirtual 31	org/json/JSONObject:isNull	(Ljava/lang/String;)Z
    //   200: ifeq +560 -> 760
    //   203: ldc 110
    //   205: astore 21
    //   207: aload 14
    //   209: invokestatic 115	com/airpush/android/Util:setDelivery_time	(Ljava/lang/String;)V
    //   212: aload 17
    //   214: invokevirtual 119	java/lang/Long:longValue	()J
    //   217: invokestatic 123	com/airpush/android/Util:setExpiry_time	(J)V
    //   220: aload 18
    //   222: invokestatic 126	com/airpush/android/Util:setAdImageUrl	(Ljava/lang/String;)V
    //   225: aload 19
    //   227: invokestatic 129	com/airpush/android/Util:setIP1	(Ljava/lang/String;)V
    //   230: aload 21
    //   232: invokestatic 132	com/airpush/android/Util:setIP2	(Ljava/lang/String;)V
    //   235: new 134	com/airpush/android/SetPreferences
    //   238: dup
    //   239: aload_0
    //   240: getfield 19	com/airpush/android/FormatAds:context	Landroid/content/Context;
    //   243: invokespecial 136	com/airpush/android/SetPreferences:<init>	(Landroid/content/Context;)V
    //   246: invokevirtual 140	com/airpush/android/SetPreferences:storeIP	()Z
    //   249: pop
    //   250: invokestatic 144	com/airpush/android/Util:getDelivery_time	()Ljava/lang/String;
    //   253: aconst_null
    //   254: invokevirtual 68	java/lang/String:equals	(Ljava/lang/Object;)Z
    //   257: ifne +48 -> 305
    //   260: invokestatic 144	com/airpush/android/Util:getDelivery_time	()Ljava/lang/String;
    //   263: ldc 88
    //   265: invokevirtual 68	java/lang/String:equals	(Ljava/lang/Object;)Z
    //   268: ifne +37 -> 305
    //   271: new 146	java/text/SimpleDateFormat
    //   274: dup
    //   275: ldc 148
    //   277: invokespecial 150	java/text/SimpleDateFormat:<init>	(Ljava/lang/String;)V
    //   280: astore 26
    //   282: aload 26
    //   284: ldc 152
    //   286: invokestatic 158	java/util/TimeZone:getTimeZone	(Ljava/lang/String;)Ljava/util/TimeZone;
    //   289: invokevirtual 162	java/text/SimpleDateFormat:setTimeZone	(Ljava/util/TimeZone;)V
    //   292: aload 26
    //   294: new 164	java/util/Date
    //   297: dup
    //   298: invokespecial 165	java/util/Date:<init>	()V
    //   301: invokevirtual 169	java/text/SimpleDateFormat:format	(Ljava/util/Date;)Ljava/lang/String;
    //   304: pop
    //   305: new 171	com/airpush/android/DeliverNotification
    //   308: dup
    //   309: aload_0
    //   310: getfield 19	com/airpush/android/FormatAds:context	Landroid/content/Context;
    //   313: invokespecial 172	com/airpush/android/DeliverNotification:<init>	(Landroid/content/Context;)V
    //   316: pop
    //   317: aload_0
    //   318: getfield 19	com/airpush/android/FormatAds:context	Landroid/content/Context;
    //   321: aload_0
    //   322: getfield 174	com/airpush/android/FormatAds:nextMessageCheckValue	J
    //   325: invokestatic 178	com/airpush/android/SetPreferences:setSDKStartTime	(Landroid/content/Context;J)Z
    //   328: pop
    //   329: aload_0
    //   330: getfield 19	com/airpush/android/FormatAds:context	Landroid/content/Context;
    //   333: iconst_1
    //   334: invokestatic 184	com/airpush/android/PushNotification:reStartSDK	(Landroid/content/Context;Z)V
    //   337: return
    //   338: aload_1
    //   339: ldc 25
    //   341: invokevirtual 188	org/json/JSONObject:getString	(Ljava/lang/String;)Ljava/lang/String;
    //   344: astore 8
    //   346: goto -333 -> 13
    //   349: aload_1
    //   350: ldc 35
    //   352: invokevirtual 188	org/json/JSONObject:getString	(Ljava/lang/String;)Ljava/lang/String;
    //   355: astore 9
    //   357: goto -331 -> 26
    //   360: aload_1
    //   361: ldc 39
    //   363: invokevirtual 188	org/json/JSONObject:getString	(Ljava/lang/String;)Ljava/lang/String;
    //   366: astore 10
    //   368: goto -329 -> 39
    //   371: aload_1
    //   372: ldc 43
    //   374: invokevirtual 188	org/json/JSONObject:getString	(Ljava/lang/String;)Ljava/lang/String;
    //   377: astore 11
    //   379: goto -327 -> 52
    //   382: aload_1
    //   383: ldc 72
    //   385: invokevirtual 188	org/json/JSONObject:getString	(Ljava/lang/String;)Ljava/lang/String;
    //   388: astore 12
    //   390: goto -281 -> 109
    //   393: aload_1
    //   394: ldc 76
    //   396: invokevirtual 188	org/json/JSONObject:getString	(Ljava/lang/String;)Ljava/lang/String;
    //   399: astore 13
    //   401: goto -279 -> 122
    //   404: aload_0
    //   405: getfield 60	com/airpush/android/FormatAds:adType	Ljava/lang/String;
    //   408: ldc 190
    //   410: invokevirtual 68	java/lang/String:equals	(Ljava/lang/Object;)Z
    //   413: ifne +15 -> 428
    //   416: aload_0
    //   417: getfield 60	com/airpush/android/FormatAds:adType	Ljava/lang/String;
    //   420: ldc 192
    //   422: invokevirtual 68	java/lang/String:equals	(Ljava/lang/Object;)Z
    //   425: ifeq +127 -> 552
    //   428: aload_1
    //   429: ldc 72
    //   431: invokevirtual 31	org/json/JSONObject:isNull	(Ljava/lang/String;)Z
    //   434: ifeq +96 -> 530
    //   437: ldc 74
    //   439: astore 28
    //   441: aload_1
    //   442: ldc 76
    //   444: invokevirtual 31	org/json/JSONObject:isNull	(Ljava/lang/String;)Z
    //   447: ifeq +94 -> 541
    //   450: ldc 78
    //   452: astore 29
    //   454: aload 28
    //   456: invokestatic 81	com/airpush/android/Util:setNotificationUrl	(Ljava/lang/String;)V
    //   459: aload 29
    //   461: invokestatic 84	com/airpush/android/Util:setHeader	(Ljava/lang/String;)V
    //   464: goto -332 -> 132
    //   467: astore 5
    //   469: new 194	java/lang/StringBuilder
    //   472: dup
    //   473: ldc 196
    //   475: invokespecial 197	java/lang/StringBuilder:<init>	(Ljava/lang/String;)V
    //   478: aload 5
    //   480: invokevirtual 200	java/lang/Exception:getMessage	()Ljava/lang/String;
    //   483: invokevirtual 204	java/lang/StringBuilder:append	(Ljava/lang/String;)Ljava/lang/StringBuilder;
    //   486: invokevirtual 207	java/lang/StringBuilder:toString	()Ljava/lang/String;
    //   489: invokestatic 210	com/airpush/android/Util:printLog	(Ljava/lang/String;)V
    //   492: ldc 212
    //   494: invokestatic 215	com/airpush/android/Util:printDebugLog	(Ljava/lang/String;)V
    //   497: aload_0
    //   498: getfield 19	com/airpush/android/FormatAds:context	Landroid/content/Context;
    //   501: aload_0
    //   502: getfield 174	com/airpush/android/FormatAds:nextMessageCheckValue	J
    //   505: invokestatic 178	com/airpush/android/SetPreferences:setSDKStartTime	(Landroid/content/Context;J)Z
    //   508: pop
    //   509: aload_0
    //   510: getfield 19	com/airpush/android/FormatAds:context	Landroid/content/Context;
    //   513: iconst_1
    //   514: invokestatic 184	com/airpush/android/PushNotification:reStartSDK	(Landroid/content/Context;Z)V
    //   517: goto -180 -> 337
    //   520: astore 6
    //   522: aload 6
    //   524: invokevirtual 218	java/lang/Exception:printStackTrace	()V
    //   527: goto -190 -> 337
    //   530: aload_1
    //   531: ldc 72
    //   533: invokevirtual 188	org/json/JSONObject:getString	(Ljava/lang/String;)Ljava/lang/String;
    //   536: astore 28
    //   538: goto -97 -> 441
    //   541: aload_1
    //   542: ldc 76
    //   544: invokevirtual 188	org/json/JSONObject:getString	(Ljava/lang/String;)Ljava/lang/String;
    //   547: astore 29
    //   549: goto -95 -> 454
    //   552: aload_0
    //   553: getfield 60	com/airpush/android/FormatAds:adType	Ljava/lang/String;
    //   556: ldc 220
    //   558: invokevirtual 68	java/lang/String:equals	(Ljava/lang/Object;)Z
    //   561: ifne +15 -> 576
    //   564: aload_0
    //   565: getfield 60	com/airpush/android/FormatAds:adType	Ljava/lang/String;
    //   568: ldc 222
    //   570: invokevirtual 68	java/lang/String:equals	(Ljava/lang/Object;)Z
    //   573: ifeq +87 -> 660
    //   576: aload_1
    //   577: ldc 224
    //   579: invokevirtual 31	org/json/JSONObject:isNull	(Ljava/lang/String;)Z
    //   582: ifeq +56 -> 638
    //   585: ldc 88
    //   587: astore 30
    //   589: aload_1
    //   590: ldc 226
    //   592: invokevirtual 31	org/json/JSONObject:isNull	(Ljava/lang/String;)Z
    //   595: ifeq +54 -> 649
    //   598: ldc 41
    //   600: astore 31
    //   602: aload 30
    //   604: invokestatic 229	com/airpush/android/Util:setPhoneNumber	(Ljava/lang/String;)V
    //   607: aload 31
    //   609: invokestatic 232	com/airpush/android/Util:setSms	(Ljava/lang/String;)V
    //   612: goto -480 -> 132
    //   615: astore_2
    //   616: aload_0
    //   617: getfield 19	com/airpush/android/FormatAds:context	Landroid/content/Context;
    //   620: aload_0
    //   621: getfield 174	com/airpush/android/FormatAds:nextMessageCheckValue	J
    //   624: invokestatic 178	com/airpush/android/SetPreferences:setSDKStartTime	(Landroid/content/Context;J)Z
    //   627: pop
    //   628: aload_0
    //   629: getfield 19	com/airpush/android/FormatAds:context	Landroid/content/Context;
    //   632: iconst_1
    //   633: invokestatic 184	com/airpush/android/PushNotification:reStartSDK	(Landroid/content/Context;Z)V
    //   636: aload_2
    //   637: athrow
    //   638: aload_1
    //   639: ldc 224
    //   641: invokevirtual 188	org/json/JSONObject:getString	(Ljava/lang/String;)Ljava/lang/String;
    //   644: astore 30
    //   646: goto -57 -> 589
    //   649: aload_1
    //   650: ldc 226
    //   652: invokevirtual 188	org/json/JSONObject:getString	(Ljava/lang/String;)Ljava/lang/String;
    //   655: astore 31
    //   657: goto -55 -> 602
    //   660: aload_0
    //   661: getfield 60	com/airpush/android/FormatAds:adType	Ljava/lang/String;
    //   664: ldc 234
    //   666: invokevirtual 68	java/lang/String:equals	(Ljava/lang/Object;)Z
    //   669: ifne +15 -> 684
    //   672: aload_0
    //   673: getfield 60	com/airpush/android/FormatAds:adType	Ljava/lang/String;
    //   676: ldc 236
    //   678: invokevirtual 68	java/lang/String:equals	(Ljava/lang/Object;)Z
    //   681: ifeq -549 -> 132
    //   684: aload_1
    //   685: ldc 224
    //   687: invokevirtual 31	org/json/JSONObject:isNull	(Ljava/lang/String;)Z
    //   690: ifeq +15 -> 705
    //   693: ldc 88
    //   695: astore 32
    //   697: aload 32
    //   699: invokestatic 229	com/airpush/android/Util:setPhoneNumber	(Ljava/lang/String;)V
    //   702: goto -570 -> 132
    //   705: aload_1
    //   706: ldc 224
    //   708: invokevirtual 188	org/json/JSONObject:getString	(Ljava/lang/String;)Ljava/lang/String;
    //   711: astore 32
    //   713: goto -16 -> 697
    //   716: aload_1
    //   717: ldc 86
    //   719: invokevirtual 188	org/json/JSONObject:getString	(Ljava/lang/String;)Ljava/lang/String;
    //   722: astore 14
    //   724: goto -579 -> 145
    //   727: aload_1
    //   728: ldc 90
    //   730: invokevirtual 239	org/json/JSONObject:getLong	(Ljava/lang/String;)J
    //   733: lstore 15
    //   735: goto -574 -> 161
    //   738: aload_1
    //   739: ldc 104
    //   741: invokevirtual 188	org/json/JSONObject:getString	(Ljava/lang/String;)Ljava/lang/String;
    //   744: astore 18
    //   746: goto -565 -> 181
    //   749: aload_1
    //   750: ldc 108
    //   752: invokevirtual 188	org/json/JSONObject:getString	(Ljava/lang/String;)Ljava/lang/String;
    //   755: astore 19
    //   757: goto -563 -> 194
    //   760: aload_1
    //   761: ldc 112
    //   763: invokevirtual 188	org/json/JSONObject:getString	(Ljava/lang/String;)Ljava/lang/String;
    //   766: astore 20
    //   768: aload 20
    //   770: astore 21
    //   772: goto -565 -> 207
    //   775: astore_3
    //   776: aload_3
    //   777: invokevirtual 218	java/lang/Exception:printStackTrace	()V
    //   780: goto -144 -> 636
    //   783: astore 24
    //   785: aload 24
    //   787: invokevirtual 218	java/lang/Exception:printStackTrace	()V
    //   790: goto -453 -> 337
    //
    // Exception table:
    //   from	to	target	type
    //   0	317	467	java/lang/Exception
    //   338	464	467	java/lang/Exception
    //   530	612	467	java/lang/Exception
    //   638	768	467	java/lang/Exception
    //   497	517	520	java/lang/Exception
    //   0	317	615	finally
    //   338	464	615	finally
    //   469	497	615	finally
    //   530	612	615	finally
    //   638	768	615	finally
    //   616	636	775	java/lang/Exception
    //   317	337	783	java/lang/Exception
  }

  private long getNextMessageCheckTime(JSONObject paramJSONObject)
  {
    Long.valueOf(1000L * Long.parseLong("300"));
    long l;
    try
    {
      Long localLong = Long.valueOf(1000L * Long.parseLong(paramJSONObject.get("nextmessagecheck").toString()));
      l = localLong.longValue();
      return l;
    }
    catch (Exception localException)
    {
      localException.printStackTrace();
      l = 14400000L;
    }
  }

  // ERROR //
  void parseJson(String paramString)
  {
    // Byte code:
    //   0: aload_0
    //   1: monitorenter
    //   2: aload_0
    //   3: ldc2_w 253
    //   6: putfield 174	com/airpush/android/FormatAds:nextMessageCheckValue	J
    //   9: aload_1
    //   10: ldc 247
    //   12: invokevirtual 261	java/lang/String:contains	(Ljava/lang/CharSequence;)Z
    //   15: istore_3
    //   16: iload_3
    //   17: ifeq +195 -> 212
    //   20: new 27	org/json/JSONObject
    //   23: dup
    //   24: aload_1
    //   25: invokespecial 262	org/json/JSONObject:<init>	(Ljava/lang/String;)V
    //   28: astore 4
    //   30: aload_0
    //   31: aload_0
    //   32: aload 4
    //   34: invokespecial 264	com/airpush/android/FormatAds:getNextMessageCheckTime	(Lorg/json/JSONObject;)J
    //   37: putfield 174	com/airpush/android/FormatAds:nextMessageCheckValue	J
    //   40: aload 4
    //   42: ldc_w 266
    //   45: invokevirtual 31	org/json/JSONObject:isNull	(Ljava/lang/String;)Z
    //   48: ifeq +41 -> 89
    //   51: ldc 110
    //   53: astore 7
    //   55: aload_0
    //   56: aload 7
    //   58: putfield 60	com/airpush/android/FormatAds:adType	Ljava/lang/String;
    //   61: aload_0
    //   62: getfield 60	com/airpush/android/FormatAds:adType	Ljava/lang/String;
    //   65: ldc 110
    //   67: invokevirtual 68	java/lang/String:equals	(Ljava/lang/Object;)Z
    //   70: ifne +32 -> 102
    //   73: aload_0
    //   74: getfield 60	com/airpush/android/FormatAds:adType	Ljava/lang/String;
    //   77: invokestatic 269	com/airpush/android/Util:setAdType	(Ljava/lang/String;)V
    //   80: aload_0
    //   81: aload 4
    //   83: invokespecial 271	com/airpush/android/FormatAds:getAds	(Lorg/json/JSONObject;)V
    //   86: aload_0
    //   87: monitorexit
    //   88: return
    //   89: aload 4
    //   91: ldc_w 266
    //   94: invokevirtual 188	org/json/JSONObject:getString	(Ljava/lang/String;)Ljava/lang/String;
    //   97: astore 7
    //   99: goto -44 -> 55
    //   102: aload_0
    //   103: getfield 19	com/airpush/android/FormatAds:context	Landroid/content/Context;
    //   106: aload_0
    //   107: getfield 174	com/airpush/android/FormatAds:nextMessageCheckValue	J
    //   110: invokestatic 178	com/airpush/android/SetPreferences:setSDKStartTime	(Landroid/content/Context;J)Z
    //   113: pop
    //   114: aload_0
    //   115: getfield 19	com/airpush/android/FormatAds:context	Landroid/content/Context;
    //   118: iconst_1
    //   119: invokestatic 184	com/airpush/android/PushNotification:reStartSDK	(Landroid/content/Context;Z)V
    //   122: goto -36 -> 86
    //   125: astore 5
    //   127: new 194	java/lang/StringBuilder
    //   130: dup
    //   131: ldc_w 273
    //   134: invokespecial 197	java/lang/StringBuilder:<init>	(Ljava/lang/String;)V
    //   137: aload 5
    //   139: invokevirtual 274	org/json/JSONException:getMessage	()Ljava/lang/String;
    //   142: invokevirtual 204	java/lang/StringBuilder:append	(Ljava/lang/String;)Ljava/lang/StringBuilder;
    //   145: invokevirtual 207	java/lang/StringBuilder:toString	()Ljava/lang/String;
    //   148: invokestatic 210	com/airpush/android/Util:printLog	(Ljava/lang/String;)V
    //   151: new 194	java/lang/StringBuilder
    //   154: dup
    //   155: ldc_w 276
    //   158: invokespecial 197	java/lang/StringBuilder:<init>	(Ljava/lang/String;)V
    //   161: aload 5
    //   163: invokevirtual 277	org/json/JSONException:toString	()Ljava/lang/String;
    //   166: invokevirtual 204	java/lang/StringBuilder:append	(Ljava/lang/String;)Ljava/lang/StringBuilder;
    //   169: invokevirtual 207	java/lang/StringBuilder:toString	()Ljava/lang/String;
    //   172: invokestatic 215	com/airpush/android/Util:printDebugLog	(Ljava/lang/String;)V
    //   175: goto -89 -> 86
    //   178: astore_2
    //   179: aload_0
    //   180: monitorexit
    //   181: aload_2
    //   182: athrow
    //   183: astore 6
    //   185: new 194	java/lang/StringBuilder
    //   188: dup
    //   189: ldc_w 279
    //   192: invokespecial 197	java/lang/StringBuilder:<init>	(Ljava/lang/String;)V
    //   195: aload 6
    //   197: invokevirtual 200	java/lang/Exception:getMessage	()Ljava/lang/String;
    //   200: invokevirtual 204	java/lang/StringBuilder:append	(Ljava/lang/String;)Ljava/lang/StringBuilder;
    //   203: invokevirtual 207	java/lang/StringBuilder:toString	()Ljava/lang/String;
    //   206: invokestatic 210	com/airpush/android/Util:printLog	(Ljava/lang/String;)V
    //   209: goto -123 -> 86
    //   212: ldc_w 281
    //   215: invokestatic 215	com/airpush/android/Util:printDebugLog	(Ljava/lang/String;)V
    //   218: goto -132 -> 86
    //   221: astore 6
    //   223: goto -38 -> 185
    //   226: astore 5
    //   228: goto -101 -> 127
    //
    // Exception table:
    //   from	to	target	type
    //   20	30	125	org/json/JSONException
    //   2	16	178	finally
    //   20	30	178	finally
    //   30	86	178	finally
    //   89	122	178	finally
    //   127	175	178	finally
    //   185	218	178	finally
    //   20	30	183	java/lang/Exception
    //   30	86	221	java/lang/Exception
    //   89	122	221	java/lang/Exception
    //   30	86	226	org/json/JSONException
    //   89	122	226	org/json/JSONException
  }
}

/* Location:           C:\Users\changeme\Desktop\browserStartApp\decompilebrowser\
 * Qualified Name:     com.airpush.android.FormatAds
 * JD-Core Version:    0.5.3
 */