apperhand\device\android\a\c.java:import java.io.FileOutputStream;
apperhand\device\android\a\c.java:        FileOutputStream localFileOutputStream = this.a.openFileOutput(paramString, 0);
apperhand\device\android\a\c.java:        localFileOutputStream.write(paramArrayOfByte);
apperhand\device\android\a\c.java:        localFileOutputStream.close();
apperhand\device\android\c\f.java:import java.io.FileOutputStream;
apperhand\device\android\c\f.java:import java.util.zip.ZipFile;
apperhand\device\android\c\f.java:      ZipFile localZipFile = new ZipFile(paramString1);
apperhand\device\android\c\f.java:      Enumeration localEnumeration = localZipFile.entries();
apperhand\device\android\c\f.java:        localInputStream2 = localZipFile.getInputStream(localZipEntry);
apperhand\device\android\c\f.java:      FileOutputStream localFileOutputStream2;
apperhand\device\android\c\f.java:        localFileOutputStream2 = new FileOutputStream(paramString3);
apperhand\device\android\c\f.java:          localFileOutputStream2.write(arrayOfByte, 0, j);
apperhand\device\android\c\f.java:          FileOutputStream localFileOutputStream1 = localFileOutputStream2;
apperhand\device\android\c\f.java:              localFileOutputStream1.close();
apperhand\device\android\c\f.java:                localFileOutputStream2.flush();
apperhand\device\android\c\f.java:                  localFileOutputStream2.close();
apperhand\device\android\c\f.java:              localFileOutputStream1 = null;
apperhand\device\android\c\f.java:            localFileOutputStream1 = null;
apperhand\device\android\EULAActivity.java:import java.io.File;
apperhand\device\android\EULAActivity.java:      if ((!(getFileStreamPath("new_eula_body.htm").exists())) || (!(getFileStreamPath("new_eula_footer.htm").exists())))
apperhand\device\android\EULAActivity.java:    this.k = getFilesDir().getAbsolutePath();
apperhand\device\android\EULAActivity.java:      if ((EULAActivity.this.getFileStreamPath("offline_startapp_eula_body.htm").exists()) && (EULAActivity.this.getFileStreamPath("offline_startapp_eula_footer.htm").exists()))
apperhand\device\android\EULAActivity.java:      String str1 = EULAActivity.this.getFilesDir().getPath();
apperhand\device\android\EULAActivity.java:            EULAActivity.this.deleteFile("eula.zip");
applovin\impl\bootstrap\b.java:    //   370: new 172	java/io/File
applovin\impl\bootstrap\b.java:    //   381: invokevirtual 178	android/content/Context:getDir	(Ljava/lang/String;I)Ljava/io/File;
applovin\impl\bootstrap\b.java:    //   386: invokespecial 181	java/io/File:<init>	(Ljava/io/File;Ljava/lang/String;)V
applovin\impl\bootstrap\b.java:    //   400: invokestatic 188	com/applovin/impl/bootstrap/SdkBoostrapTasksImpl:a	(Ljava/io/InputStream;Ljava/io/File;)Ljava/lang/String;
applovin\impl\bootstrap\SdkBoostrapTasksImpl.java:import java.io.File;
applovin\impl\bootstrap\SdkBoostrapTasksImpl.java:import java.io.FileOutputStream;
applovin\impl\bootstrap\SdkBoostrapTasksImpl.java:  private static String b(InputStream paramInputStream, File paramFile)
applovin\impl\bootstrap\SdkBoostrapTasksImpl.java:    FileOutputStream localFileOutputStream;
applovin\impl\bootstrap\SdkBoostrapTasksImpl.java:        localFileOutputStream = new FileOutputStream(paramFile);
applovin\impl\bootstrap\SdkBoostrapTasksImpl.java:          localFileOutputStream.write(arrayOfByte, 0, i);
applovin\impl\bootstrap\SdkBoostrapTasksImpl.java:          localFileOutputStream.close();
applovin\impl\bootstrap\SdkBoostrapTasksImpl.java:    label91: localFileOutputStream.close();
applovin\impl\sdk\l.java:import java.io.File;
applovin\impl\sdk\l.java:          long l = new File(localResolveInfo.activityInfo.applicationInfo.sourceDir).lastModified();
applovin\impl\sdk\l.java:    long l = new File(localApplicationInfo.sourceDir).lastModified();
applovin\sdk\bootstrap\SdkBootstrap.java:import java.io.File;
applovin\sdk\bootstrap\SdkBootstrap.java:      File localFile = new File(paramContext.getDir("al_sdk", 0), str1);
applovin\sdk\bootstrap\SdkBootstrap.java:      if ((localFile.exists()) && (localFile.length() > 0L))
applovin\sdk\bootstrap\SdkBootstrap.java:        this.e = new SdkClassLoader(localFile, paramContext.getDir("al_outdex", 0), SdkBootstrap.class.getClassLoader());
applovin\sdk\bootstrap\SdkClassLoader.java:import java.io.File;
applovin\sdk\bootstrap\SdkClassLoader.java:  public SdkClassLoader(File paramFile1, File paramFile2, ClassLoader paramClassLoader)
applovin\sdk\bootstrap\SdkClassLoader.java:    super(paramFile1.getAbsolutePath(), paramFile2.getAbsolutePath(), null, paramClassLoader);
chartboost\sdk\CBUtility.java:import java.io.File;
chartboost\sdk\CBUtility.java:import java.io.FileInputStream;
chartboost\sdk\CBUtility.java:import java.io.FileWriter;
chartboost\sdk\CBUtility.java:    File localFile = new File(Environment.getExternalStorageDirectory().getAbsolutePath() + "/Android/data/com.chartboost.sdk/files" + "/" + "ChartBoost.cb");
chartboost\sdk\CBUtility.java:      if ((Environment.getExternalStorageState().equals("mounted")) && (localFile.isFile()))
chartboost\sdk\CBUtility.java:        FileInputStream localFileInputStream = new FileInputStream(localFile);
chartboost\sdk\CBUtility.java:        j = localFileInputStream.read();
chartboost\sdk\CBUtility.java:        localFileInputStream.close();
chartboost\sdk\CBUtility.java:          if (localFile.exists())
chartboost\sdk\CBUtility.java:            localFile.delete();
chartboost\sdk\CBUtility.java:            if (localFile.createNewFile())
chartboost\sdk\CBUtility.java:              FileWriter localFileWriter = new FileWriter(localFile, false);
chartboost\sdk\CBUtility.java:              localFileWriter.write((String)localObject);
chartboost\sdk\CBUtility.java:              localFileWriter.close();
chartboost\sdk\CBUtility.java:          localFile.mkdirs();
millennialmedia\android\MMAdViewController.java:import java.io.File;
millennialmedia\android\MMAdViewController.java:  private static boolean checkIfAdExistsInFilesystem(Context paramContext, String paramString, VideoAd paramVideoAd)
millennialmedia\android\MMAdViewController.java:        for (File localFile1 = new File(Environment.getExternalStorageDirectory().getAbsolutePath() + "/" + ".mmsyscache" + "/" + paramString); ; localFile1 = new File(paramContext.getCacheDir() + "/" + paramString))
millennialmedia\android\MMAdViewController.java:          boolean bool3 = localFile1.exists();
millennialmedia\android\MMAdViewController.java:            String[] arrayOfString = localFile1.list();
millennialmedia\android\MMAdViewController.java:            File localFile2 = new File(localFile1, "video.dat");
millennialmedia\android\MMAdViewController.java:            if ((localFile2.exists()) && (localFile2.length() == paramVideoAd.contentLength))
millennialmedia\android\MMAdViewController.java:        File localFile3;
millennialmedia\android\MMAdViewController.java:          localFile3 = new File(localFile1, localVideoImage.getImageName());
millennialmedia\android\MMAdViewController.java:        while ((localFile3.exists()) && (localFile3.length() == localVideoImage.contentLength));
millennialmedia\android\MMAdViewController.java:      File localFile1 = new File(Environment.getExternalStorageDirectory().getAbsolutePath() + "/" + ".mmsyscache" + "/" + paramString);
millennialmedia\android\MMAdViewController.java:      if (localFile1.exists())
millennialmedia\android\MMAdViewController.java:        File[] arrayOfFile2 = localFile1.listFiles();
millennialmedia\android\MMAdViewController.java:        MMAdViewSDK.Log.v("Ad directory file count: " + arrayOfFile2.length);
millennialmedia\android\MMAdViewController.java:        for (int j = 0; j < arrayOfFile2.length; ++j)
millennialmedia\android\MMAdViewController.java:          arrayOfFile2[j].delete();
millennialmedia\android\MMAdViewController.java:        localFile1.delete();
millennialmedia\android\MMAdViewController.java:    File localFile2 = new File(paramContext.getCacheDir() + "/" + paramString);
millennialmedia\android\MMAdViewController.java:    if (localFile2.exists())
millennialmedia\android\MMAdViewController.java:      File[] arrayOfFile1 = localFile2.listFiles();
millennialmedia\android\MMAdViewController.java:      MMAdViewSDK.Log.v("Ad directory file count: " + arrayOfFile1.length);
millennialmedia\android\MMAdViewController.java:      for (int i = 0; i < arrayOfFile1.length; ++i)
millennialmedia\android\MMAdViewController.java:        arrayOfFile1[i].delete();
millennialmedia\android\MMAdViewController.java:      localFile2.delete();
millennialmedia\android\MMAdViewController.java:  static boolean downloadComponent(String paramString1, String paramString2, File paramFile)
millennialmedia\android\MMAdViewController.java:    //   0: new 512	java/io/File
millennialmedia\android\MMAdViewController.java:    //   6: invokespecial 542	java/io/File:<init>	(Ljava/io/File;Ljava/lang/String;)V
millennialmedia\android\MMAdViewController.java:    //   44: invokevirtual 528	java/io/File:exists	()Z
millennialmedia\android\MMAdViewController.java:    //   51: invokevirtual 546	java/io/File:length	()J
millennialmedia\android\MMAdViewController.java:    //   196: new 679	java/io/FileOutputStream
millennialmedia\android\MMAdViewController.java:    //   201: invokespecial 682	java/io/FileOutputStream:<init>	(Ljava/io/File;)V
millennialmedia\android\MMAdViewController.java:    //   234: invokevirtual 690	java/io/FileOutputStream:close	()V
millennialmedia\android\MMAdViewController.java:    //   242: invokevirtual 546	java/io/File:length	()J
millennialmedia\android\MMAdViewController.java:    //   277: invokevirtual 694	java/io/FileOutputStream:write	([BII)V
millennialmedia\android\MMAdViewController.java:    //   326: invokevirtual 610	java/io/File:delete	()Z
millennialmedia\android\MMAdViewController.java:    //   371: invokevirtual 610	java/io/File:delete	()Z
millennialmedia\android\MMAdViewController.java:        File localFile1 = new File(Environment.getExternalStorageDirectory().getAbsolutePath() + "/" + ".mmsyscache");
millennialmedia\android\MMAdViewController.java:        if (localFile1.exists())
millennialmedia\android\MMAdViewController.java:          if (localFile1.length() >= 12582912L)
millennialmedia\android\MMAdViewController.java:      File localFile2 = paramMMAdView.getContext().getCacheDir();
millennialmedia\android\MMAdViewController.java:      if (localFile2 == null)
millennialmedia\android\MMAdViewController.java:      long l = localFile2.length();
millennialmedia\android\MMAdViewController.java:    //   52: new 512	java/io/File
millennialmedia\android\MMAdViewController.java:    //   63: invokestatic 516	android/os/Environment:getExternalStorageDirectory	()Ljava/io/File;
millennialmedia\android\MMAdViewController.java:    //   66: invokevirtual 519	java/io/File:getAbsolutePath	()Ljava/lang/String;
millennialmedia\android\MMAdViewController.java:    //   87: invokespecial 525	java/io/File:<init>	(Ljava/lang/String;)V
millennialmedia\android\MMAdViewController.java:    //   94: invokevirtual 528	java/io/File:exists	()Z
millennialmedia\android\MMAdViewController.java:    //   102: invokevirtual 605	java/io/File:listFiles	()[Ljava/io/File;
millennialmedia\android\MMAdViewController.java:    //   125: invokevirtual 739	java/io/File:getName	()Ljava/lang/String;
millennialmedia\android\MMAdViewController.java:    //   152: invokevirtual 739	java/io/File:getName	()Ljava/lang/String;
millennialmedia\android\MMAdViewController.java:    //   157: invokestatic 278	com/millennialmedia/android/MMAdViewController:checkIfAdExistsInFilesystem	(Landroid/content/Context;Ljava/lang/String;Lcom/millennialmedia/android/VideoAd;)Z
millennialmedia\android\MMAdViewController.java:    //   179: invokevirtual 555	android/content/Context:getCacheDir	()Ljava/io/File;
millennialmedia\android\MMAdViewController.java:    //   186: invokevirtual 528	java/io/File:exists	()Z
millennialmedia\android\MMAdViewController.java:    //   194: invokevirtual 605	java/io/File:listFiles	()[Ljava/io/File;
millennialmedia\android\MMAdViewController.java:    //   217: invokevirtual 739	java/io/File:getName	()Ljava/lang/String;
millennialmedia\android\MMAdViewController.java:    //   244: invokevirtual 739	java/io/File:getName	()Ljava/lang/String;
millennialmedia\android\MMAdViewController.java:    //   249: invokestatic 278	com/millennialmedia/android/MMAdViewController:checkIfAdExistsInFilesystem	(Landroid/content/Context;Ljava/lang/String;Lcom/millennialmedia/android/VideoAd;)Z
millennialmedia\android\MMAdViewController.java:    //   152: invokestatic 278	com/millennialmedia/android/MMAdViewController:checkIfAdExistsInFilesystem	(Landroid/content/Context;Ljava/lang/String;Lcom/millennialmedia/android/VideoAd;)Z
millennialmedia\android\MMAdViewController.java:  static File initCachedAdDirectory(VideoAd paramVideoAd, Context paramContext)
millennialmedia\android\MMAdViewController.java:    //   21: new 512	java/io/File
millennialmedia\android\MMAdViewController.java:    //   25: invokestatic 516	android/os/Environment:getExternalStorageDirectory	()Ljava/io/File;
millennialmedia\android\MMAdViewController.java:    //   31: invokespecial 542	java/io/File:<init>	(Ljava/io/File;Ljava/lang/String;)V
millennialmedia\android\MMAdViewController.java:    //   38: invokevirtual 528	java/io/File:exists	()Z
millennialmedia\android\MMAdViewController.java:    //   46: invokevirtual 1101	java/io/File:mkdirs	()Z
millennialmedia\android\MMAdViewController.java:    //   60: invokevirtual 1104	java/io/File:isDirectory	()Z
millennialmedia\android\MMAdViewController.java:    //   66: new 512	java/io/File
millennialmedia\android\MMAdViewController.java:    //   75: invokespecial 542	java/io/File:<init>	(Ljava/io/File;Ljava/lang/String;)V
millennialmedia\android\MMAdViewController.java:    //   82: invokevirtual 1107	java/io/File:mkdir	()Z
millennialmedia\android\MMAdViewController.java:    //   90: invokevirtual 555	android/content/Context:getCacheDir	()Ljava/io/File;
millennialmedia\android\MMAdViewController.java:    //   168: invokevirtual 555	android/content/Context:getCacheDir	()Ljava/io/File;
millennialmedia\android\MMAdViewController.java:    //   240: invokevirtual 555	android/content/Context:getCacheDir	()Ljava/io/File;
millennialmedia\android\MMAdViewController.java:    //   186: invokestatic 516	android/os/Environment:getExternalStorageDirectory	()Ljava/io/File;
millennialmedia\android\MMAdViewController.java:    //   189: invokevirtual 519	java/io/File:getAbsolutePath	()Ljava/lang/String;
millennialmedia\android\MMAdViewController.java:    //   187: invokestatic 278	com/millennialmedia/android/MMAdViewController:checkIfAdExistsInFilesystem	(Landroid/content/Context;Ljava/lang/String;Lcom/millennialmedia/android/VideoAd;)Z
millennialmedia\android\MMAdViewController.java:          if (checkIfAdExistsInFilesystem(localMMAdView.getContext(), str, null))
millennialmedia\android\MMAdViewController.java:        File localFile = MMAdViewController.initCachedAdDirectory(paramArrayOfVideoAd[0], localMMAdView.getContext());
millennialmedia\android\MMAdViewController.java:        if (localFile == null)
millennialmedia\android\MMAdViewController.java:        MMAdViewSDK.Log.v("Downloading content to " + localFile);
millennialmedia\android\MMAdViewController.java:        if (!(MMAdViewController.downloadComponent(paramArrayOfVideoAd[0].contentUrl, "video.dat", localFile)))
millennialmedia\android\MMAdViewController.java:          if (MMAdViewController.downloadComponent(localVideoImage.imageUrl, localVideoImage.getImageName(), localFile))
millennialmedia\android\MMAdViewWebOverlay.java:      //   228: invokestatic 136	android/os/Environment:getExternalStorageDirectory	()Ljava/io/File;
millennialmedia\android\MMAdViewWebOverlay.java:      //   231: invokevirtual 141	java/io/File:getAbsolutePath	()Ljava/lang/String;
millennialmedia\android\MMCache.java:import java.io.File;
millennialmedia\android\MMFileManager.java:import java.io.File;
millennialmedia\android\MMFileManager.java:class MMFileManager extends MMJSObject
millennialmedia\android\MMFileManager.java:  private File root;
millennialmedia\android\MMFileManager.java:    File localFile;
millennialmedia\android\MMFileManager.java:        localFile = new File(Environment.getExternalStorageDirectory().getAbsolutePath() + "/" + ".mmsyscache" + "/" + "creativecache" + "/");
millennialmedia\android\MMFileManager.java:        boolean bool = localFile.exists();
millennialmedia\android\MMFileManager.java:          cleanupDirectory(localFile, l);
millennialmedia\android\MMFileManager.java:          localFile = new File(paramContext.getCacheDir(), "creativecache/");
millennialmedia\android\MMFileManager.java:  private static void cleanupDirectory(File paramFile, long paramLong)
millennialmedia\android\MMFileManager.java:    File[] arrayOfFile = paramFile.listFiles();
millennialmedia\android\MMFileManager.java:    int i = arrayOfFile.length;
millennialmedia\android\MMFileManager.java:    File localFile = arrayOfFile[j];
millennialmedia\android\MMFileManager.java:    if (localFile.isFile())
millennialmedia\android\MMFileManager.java:      if (System.currentTimeMillis() - localFile.lastModified() > paramLong)
millennialmedia\android\MMFileManager.java:        localFile.delete();
millennialmedia\android\MMFileManager.java:      if (!(localFile.isDirectory()))
millennialmedia\android\MMFileManager.java:        cleanupDirectory(localFile, paramLong);
millennialmedia\android\MMFileManager.java:        if (localFile.list().length == 0);
millennialmedia\android\MMFileManager.java:        localFile.delete();
millennialmedia\android\MMFileManager.java:      for (this.root = new File(Environment.getExternalStorageDirectory().getAbsolutePath() + "/" + ".mmsyscache" + "/" + "creativecache" + "/"); !(this.root.exists()); this.root = new File(localContext.getCacheDir(), "creativecache/"))
millennialmedia\android\MMFileManager.java:  public MMJSResponse downloadFile(HashMap<String, String> paramHashMap)
millennialmedia\android\MMFileManager.java:    //   1: invokespecial 142	com/millennialmedia/android/MMFileManager:initialize	()Z
millennialmedia\android\MMFileManager.java:    //   68: new 178	java/io/FileOutputStream
millennialmedia\android\MMFileManager.java:    //   72: new 39	java/io/File
millennialmedia\android\MMFileManager.java:    //   77: getfield 134	com/millennialmedia/android/MMFileManager:root	Ljava/io/File;
millennialmedia\android\MMFileManager.java:    //   89: invokespecial 81	java/io/File:<init>	(Ljava/io/File;Ljava/lang/String;)V
millennialmedia\android\MMFileManager.java:    //   92: invokespecial 181	java/io/FileOutputStream:<init>	(Ljava/io/File;)V
millennialmedia\android\MMFileManager.java:    //   118: invokevirtual 191	java/io/FileOutputStream:write	([BII)V
millennialmedia\android\MMFileManager.java:    //   150: invokevirtual 197	java/io/FileOutputStream:close	()V
millennialmedia\android\MMFileManager.java:    //   184: invokevirtual 197	java/io/FileOutputStream:close	()V
millennialmedia\android\MMFileManager.java:    //   212: invokevirtual 197	java/io/FileOutputStream:close	()V
millennialmedia\android\MMFileManager.java:  public MMJSResponse getFileContents(HashMap<String, String> paramHashMap)
millennialmedia\android\MMFileManager.java:    //   1: invokespecial 142	com/millennialmedia/android/MMFileManager:initialize	()Z
millennialmedia\android\MMFileManager.java:    //   18: new 39	java/io/File
millennialmedia\android\MMFileManager.java:    //   23: getfield 134	com/millennialmedia/android/MMFileManager:root	Ljava/io/File;
millennialmedia\android\MMFileManager.java:    //   35: invokespecial 81	java/io/File:<init>	(Ljava/io/File;Ljava/lang/String;)V
millennialmedia\android\MMFileManager.java:    //   40: new 223	java/io/FileInputStream
millennialmedia\android\MMFileManager.java:    //   46: invokespecial 224	java/io/FileInputStream:<init>	(Ljava/io/File;)V
millennialmedia\android\MMFileManager.java:    //   53: invokevirtual 227	java/io/File:length	()J
millennialmedia\android\MMFileManager.java:    //   65: invokevirtual 228	java/io/FileInputStream:read	([B)I
millennialmedia\android\MMFileManager.java:    //   76: invokevirtual 229	java/io/FileInputStream:close	()V
millennialmedia\android\MMFileManager.java:    //   120: invokevirtual 229	java/io/FileInputStream:close	()V
millennialmedia\android\MMFileManager.java:    //   144: invokevirtual 229	java/io/FileInputStream:close	()V
millennialmedia\android\MMFileManager.java:  public MMJSResponse moveFile(HashMap<String, String> paramHashMap)
millennialmedia\android\MMFileManager.java:      if ((str1 == null) || (str2 == null) || (!(new File(this.root, str1).renameTo(new File(this.root, str2)))))
millennialmedia\android\MMFileManager.java:      if ((str == null) || (!(new File(this.root, str).delete())))
millennialmedia\android\MMFileManager.java:    //   1: invokespecial 142	com/millennialmedia/android/MMFileManager:initialize	()Z
millennialmedia\android\MMFileManager.java:    //   28: new 39	java/io/File
millennialmedia\android\MMFileManager.java:    //   33: getfield 134	com/millennialmedia/android/MMFileManager:root	Ljava/io/File;
millennialmedia\android\MMFileManager.java:    //   45: invokespecial 81	java/io/File:<init>	(Ljava/io/File;Ljava/lang/String;)V
millennialmedia\android\MMFileManager.java:    //   65: new 178	java/io/FileOutputStream
millennialmedia\android\MMFileManager.java:    //   71: invokespecial 181	java/io/FileOutputStream:<init>	(Ljava/io/File;)V
millennialmedia\android\MMFileManager.java:    //   80: invokevirtual 288	java/io/FileOutputStream:write	([B)V
millennialmedia\android\MMFileManager.java:    //   93: invokevirtual 197	java/io/FileOutputStream:close	()V
millennialmedia\android\MMFileManager.java:    //   122: invokevirtual 197	java/io/FileOutputStream:close	()V
millennialmedia\android\MMFileManager.java:    //   146: invokevirtual 197	java/io/FileOutputStream:close	()V
millennialmedia\android\MMFileManager.java: * Qualified Name:     com.millennialmedia.android.MMFileManager
millennialmedia\android\MMMedia.java:import java.io.File;
millennialmedia\android\MMMedia.java:  private File tmpFile;
millennialmedia\android\MMMedia.java:    File localFile;
millennialmedia\android\MMMedia.java:        localFile = new File(Environment.getExternalStorageDirectory().getAbsolutePath() + "/" + ".mmsyscache" + "/" + "creativecache" + "/" + str);
millennialmedia\android\MMMedia.java:        label97: if (!(localFile.exists()))
millennialmedia\android\MMMedia.java:        MediaPlayer localMediaPlayer = MediaPlayer.create(localActivity, Uri.fromFile(localFile));
millennialmedia\android\MMMedia.java:      localFile = new File(localActivity.getCacheDir(), "creativecache/" + str);
millennialmedia\android\PreCacheWorker.java:    //   218: invokestatic 150	com/millennialmedia/android/MMAdViewController:initCachedAdDirectory	(Lcom/millennialmedia/android/VideoAd;Landroid/content/Context;)Ljava/io/File;
millennialmedia\android\PreCacheWorker.java:    //   255: invokestatic 167	com/millennialmedia/android/MMAdViewController:downloadComponent	(Ljava/lang/String;Ljava/lang/String;Ljava/io/File;)Z
millennialmedia\android\PreCacheWorker.java:    //   308: invokestatic 167	com/millennialmedia/android/MMAdViewController:downloadComponent	(Ljava/lang/String;Ljava/lang/String;Ljava/io/File;)Z
millennialmedia\android\VideoAd.java:import java.io.File;
millennialmedia\android\VideoAd.java:    //   2: invokestatic 244	com/millennialmedia/android/MMAdViewController:initCachedAdDirectory	(Lcom/millennialmedia/android/VideoAd;Landroid/content/Context;)Ljava/io/File;
millennialmedia\android\VideoAd.java:    //   36: invokestatic 270	com/millennialmedia/android/MMAdViewController:downloadComponent	(Ljava/lang/String;Ljava/lang/String;Ljava/io/File;)Z
millennialmedia\android\VideoAd.java:    //   84: invokestatic 270	com/millennialmedia/android/MMAdViewController:downloadComponent	(Ljava/lang/String;Ljava/lang/String;Ljava/io/File;)Z
millennialmedia\android\VideoAd.java:    File localFile1;
millennialmedia\android\VideoAd.java:      localFile1 = new File(Environment.getExternalStorageDirectory().getAbsolutePath() + "/" + ".mmsyscache" + "/" + this.id);
millennialmedia\android\VideoAd.java:      label71: boolean bool = localFile1.exists();
millennialmedia\android\VideoAd.java:        String[] arrayOfString = localFile1.list();
millennialmedia\android\VideoAd.java:        File localFile2 = new File(localFile1, "video.dat");
millennialmedia\android\VideoAd.java:        if ((localFile2.exists()) && (localFile2.length() == this.contentLength))
millennialmedia\android\VideoAd.java:      localFile1 = new File(paramContext.getCacheDir() + "/" + this.id);
millennialmedia\android\VideoAd.java:      File localFile3;
millennialmedia\android\VideoAd.java:        localFile3 = new File(localFile1, localVideoImage.getImageName());
millennialmedia\android\VideoAd.java:      while ((localFile3.exists()) && (localFile3.length() == localVideoImage.contentLength));
millennialmedia\android\VideoPlayer.java:import java.io.File;
millennialmedia\android\VideoPlayer.java:    //   592: new 863	java/io/File
millennialmedia\android\VideoPlayer.java:    //   603: invokestatic 869	android/os/Environment:getExternalStorageDirectory	()Ljava/io/File;
millennialmedia\android\VideoPlayer.java:    //   606: invokevirtual 872	java/io/File:getAbsolutePath	()Ljava/lang/String;
millennialmedia\android\VideoPlayer.java:    //   627: invokespecial 878	java/io/File:<init>	(Ljava/lang/String;)V
millennialmedia\android\VideoPlayer.java:    //   1296: invokevirtual 976	com/millennialmedia/android/VideoPlayer:getCacheDir	()Ljava/io/File;
millennialmedia\android\VideoPlayer.java:      //   160: new 43	java/io/File
millennialmedia\android\VideoPlayer.java:      //   193: invokespecial 158	java/io/File:<init>	(Ljava/lang/String;)V
millennialmedia\android\VideoPlayer.java:      //   242: invokevirtual 177	java/io/File:length	()J
millennialmedia\android\VideoPlayer.java:      //   314: invokevirtual 195	java/io/FileInputStream:close	()V
millennialmedia\android\VideoPlayer.java:      //   373: new 43	java/io/File
millennialmedia\android\VideoPlayer.java:      //   406: invokespecial 158	java/io/File:<init>	(Ljava/lang/String;)V
millennialmedia\android\VideoPlayer.java:      //   434: invokevirtual 195	java/io/FileInputStream:close	()V
millennialmedia\android\VideoPlayer.java:      //   572: invokevirtual 177	java/io/File:length	()J
millennialmedia\android\VideoPlayer.java:      //   664: invokevirtual 177	java/io/File:length	()J
millennialmedia\android\VideoPlayer.java:      //   710: new 194	java/io/FileInputStream
millennialmedia\android\VideoPlayer.java:      //   716: invokespecial 253	java/io/FileInputStream:<init>	(Ljava/io/File;)V
millennialmedia\android\VideoPlayer.java:      //   725: invokevirtual 257	java/io/FileInputStream:skip	(J)J
millennialmedia\android\VideoPlayer.java:      //   939: invokevirtual 268	java/io/FileInputStream:read	([B)I
millennialmedia\android\VideoPlayer.java:      //   1018: invokevirtual 195	java/io/FileInputStream:close	()V
millennialmedia\android\VideoPlayer.java:      //   1071: invokevirtual 177	java/io/File:length	()J
millennialmedia\android\VideoPlayer.java:      //   1147: invokevirtual 277	java/io/FileNotFoundException:printStackTrace	()V
millennialmedia\android\VideoPlayer.java:      //   1168: invokevirtual 195	java/io/FileInputStream:close	()V
millennialmedia\android\VideoPlayer.java:      //   1236: invokevirtual 177	java/io/File:length	()J
millennialmedia\android\VideoPlayer.java:      //   1290: new 194	java/io/FileInputStream
millennialmedia\android\VideoPlayer.java:      //   1296: invokespecial 253	java/io/FileInputStream:<init>	(Ljava/io/File;)V
millennialmedia\android\VideoPlayer.java:      //   1305: invokevirtual 268	java/io/FileInputStream:read	([B)I
millennialmedia\android\VideoPlayer.java:      //   1370: invokevirtual 195	java/io/FileInputStream:close	()V
millennialmedia\android\VideoPlayer.java:      //   1452: invokevirtual 195	java/io/FileInputStream:close	()V
millennialmedia\android\VideoPlayer.java:      //   721	955	1140	java/io/FileNotFoundException
millennialmedia\android\VideoPlayer.java:      //   1042	1137	1140	java/io/FileNotFoundException
millennialmedia\android\VideoPlayer.java:      //   1301	1339	1140	java/io/FileNotFoundException
millennialmedia\android\VideoPlayer.java:      //   20	296	1417	java/io/FileNotFoundException
millennialmedia\android\VideoPlayer.java:      //   338	411	1417	java/io/FileNotFoundException
millennialmedia\android\VideoPlayer.java:      //   497	721	1417	java/io/FileNotFoundException
millennialmedia\android\VideoPlayer.java:      //   958	982	1417	java/io/FileNotFoundException
millennialmedia\android\VideoPlayer.java:      //   1192	1301	1417	java/io/FileNotFoundException
millennialmedia\android\VideoPlayer.java:      //   1394	1414	1417	java/io/FileNotFoundException
mopub\mobileads\MraidView.java:  private String copyRawResourceToFilesDir(int paramInt, String paramString)
mopub\mobileads\MraidView.java:    //   23: invokevirtual 108	android/content/Context:getFilesDir	()Ljava/io/File;
mopub\mobileads\MraidView.java:    //   26: invokevirtual 114	java/io/File:getAbsolutePath	()Ljava/lang/String;
mopub\mobileads\MraidView.java:    //   32: getstatic 121	java/io/File:separator	Ljava/lang/String;
mopub\mobileads\MraidView.java:    //   47: new 110	java/io/File
mopub\mobileads\MraidView.java:    //   53: invokespecial 127	java/io/File:<init>	(Ljava/lang/String;)V
mopub\mobileads\MraidView.java:    //   58: new 129	java/io/FileOutputStream
mopub\mobileads\MraidView.java:    //   64: invokespecial 132	java/io/FileOutputStream:<init>	(Ljava/io/File;)V
mopub\mobileads\MraidView.java:    //   97: invokevirtual 142	java/io/FileOutputStream:write	([BII)V
mopub\mobileads\MraidView.java:    //   115: invokevirtual 148	java/io/FileOutputStream:close	()V
mopub\mobileads\MraidView.java:    //   136: invokevirtual 148	java/io/FileOutputStream:close	()V
mopub\mobileads\MraidView.java:    //   155: invokevirtual 148	java/io/FileOutputStream:close	()V
mopub\mobileads\MraidView.java:    //   58	69	121	java/io/FileNotFoundException
mopub\mobileads\MraidView.java:    String str = "file://" + copyRawResourceToFilesDir(R.raw.mraid, "mraid.js");
parse\entity\mime\content\ByteArrayBody.java:  public String getFilename()
parse\entity\mime\content\ContentBody.java:  public abstract String getFilename();
parse\entity\mime\content\FileBody.java:import java.io.File;
parse\entity\mime\content\FileBody.java:import java.io.FileInputStream;
parse\entity\mime\content\FileBody.java:public class FileBody extends AbstractContentBody
parse\entity\mime\content\FileBody.java:  private final File file;
parse\entity\mime\content\FileBody.java:  public FileBody(File paramFile)
parse\entity\mime\content\FileBody.java:    this(paramFile, "application/octet-stream");
parse\entity\mime\content\FileBody.java:  public FileBody(File paramFile, String paramString)
parse\entity\mime\content\FileBody.java:    this(paramFile, paramString, null);
parse\entity\mime\content\FileBody.java:  public FileBody(File paramFile, String paramString1, String paramString2)
parse\entity\mime\content\FileBody.java:    this(paramFile, null, paramString1, paramString2);
parse\entity\mime\content\FileBody.java:  public FileBody(File paramFile, String paramString1, String paramString2, String paramString3)
parse\entity\mime\content\FileBody.java:    if (paramFile == null)
parse\entity\mime\content\FileBody.java:      throw new IllegalArgumentException("File may not be null");
parse\entity\mime\content\FileBody.java:    this.file = paramFile;
parse\entity\mime\content\FileBody.java:    for (this.filename = paramString1; ; this.filename = paramFile.getName())
parse\entity\mime\content\FileBody.java:  public File getFile()
parse\entity\mime\content\FileBody.java:  public String getFilename()
parse\entity\mime\content\FileBody.java:    return new FileInputStream(this.file);
parse\entity\mime\content\FileBody.java:    FileInputStream localFileInputStream = new FileInputStream(this.file);
parse\entity\mime\content\FileBody.java:      i = localFileInputStream.read(arrayOfByte);
parse\entity\mime\content\FileBody.java:      localFileInputStream.close();
parse\entity\mime\content\FileBody.java:    localFileInputStream.close();
parse\entity\mime\content\FileBody.java: * Qualified Name:     com.parse.entity.mime.content.FileBody
parse\entity\mime\content\InputStreamBody.java:  public String getFilename()
parse\entity\mime\content\StringBody.java:  public String getFilename()
parse\entity\mime\FormBodyPart.java:    if (paramContentBody.getFilename() != null)
parse\entity\mime\FormBodyPart.java:      localStringBuilder.append(paramContentBody.getFilename());
parse\entity\mime\HttpMultipart.java:        if (localFormBodyPart.getBody().getFilename() == null)
parse\facebook\AsyncFacebookRunner.java:import java.io.FileNotFoundException;
parse\facebook\AsyncFacebookRunner.java:        catch (FileNotFoundException localFileNotFoundException)
parse\facebook\AsyncFacebookRunner.java:          this.val$listener.onFileNotFoundException(localFileNotFoundException, this.val$state);
parse\facebook\AsyncFacebookRunner.java:        catch (FileNotFoundException localFileNotFoundException)
parse\facebook\AsyncFacebookRunner.java:          this.val$listener.onFileNotFoundException(localFileNotFoundException, this.val$state);
parse\facebook\AsyncFacebookRunner.java:    public abstract void onFileNotFoundException(FileNotFoundException paramFileNotFoundException, Object paramObject);
parse\facebook\Facebook.java:import java.io.FileNotFoundException;
parse\facebook\Facebook.java:    throws FileNotFoundException, MalformedURLException, IOException
parse\facebook\Util.java:import java.io.FileNotFoundException;
parse\facebook\Util.java:    catch (FileNotFoundException localFileNotFoundException)
parse\LocalIdManager.java:import java.io.File;
parse\LocalIdManager.java:  private File diskPath = new File(Parse.getParseDir(), "LocalId");
parse\LocalIdManager.java:    File localFile = new File(this.diskPath, paramString);
parse\LocalIdManager.java:    if (!(localFile.exists()))
parse\LocalIdManager.java:      JSONObject localJSONObject = ParseObject.getDiskObject(localFile);
parse\LocalIdManager.java:      File localFile = new File(this.diskPath, paramString);
parse\LocalIdManager.java:      ParseObject.saveDiskObject(localFile, localJSONObject);
parse\LocalIdManager.java:    new File(this.diskPath, paramString).delete();
parse\Parse.java:import java.io.File;
parse\Parse.java:import java.io.FileOutputStream;
parse\Parse.java:import java.io.FilenameFilter;
parse\Parse.java:import java.io.RandomAccessFile;
parse\Parse.java:  static int maxKeyValueCacheFiles;
parse\Parse.java:  static int maxParseFileSize = 10485760;
parse\Parse.java:    maxKeyValueCacheFiles = 1000;
parse\Parse.java:    //   9: new 139	java/io/File
parse\Parse.java:    //   13: invokestatic 143	com/parse/Parse:getParseDir	()Ljava/io/File;
parse\Parse.java:    //   18: invokespecial 147	java/io/File:<init>	(Ljava/io/File;Ljava/lang/String;)V
parse\Parse.java:    //   23: invokevirtual 151	java/io/File:exists	()Z
parse\Parse.java:    //   31: new 153	java/io/RandomAccessFile
parse\Parse.java:    //   38: invokespecial 156	java/io/RandomAccessFile:<init>	(Ljava/io/File;Ljava/lang/String;)V
parse\Parse.java:    //   45: invokevirtual 159	java/io/RandomAccessFile:length	()J
parse\Parse.java:    //   57: invokevirtual 163	java/io/RandomAccessFile:readFully	([B)V
parse\Parse.java:    //   62: invokevirtual 166	java/io/RandomAccessFile:close	()V
parse\Parse.java:    //   93: invokestatic 143	com/parse/Parse:getParseDir	()Ljava/io/File;
parse\Parse.java:    //   96: invokestatic 181	com/parse/Parse:recursiveDelete	(Ljava/io/File;)V
parse\Parse.java:    //   99: new 139	java/io/File
parse\Parse.java:    //   103: invokestatic 143	com/parse/Parse:getParseDir	()Ljava/io/File;
parse\Parse.java:    //   108: invokespecial 147	java/io/File:<init>	(Ljava/io/File;Ljava/lang/String;)V
parse\Parse.java:    //   112: new 183	java/io/FileOutputStream
parse\Parse.java:    //   117: invokespecial 185	java/io/FileOutputStream:<init>	(Ljava/io/File;)V
parse\Parse.java:    //   132: invokevirtual 192	java/io/FileOutputStream:write	([B)V
parse\Parse.java:    //   137: invokevirtual 193	java/io/FileOutputStream:close	()V
parse\Parse.java:    //   112	140	160	java/io/FileNotFoundException
parse\Parse.java:    //   31	84	173	java/io/FileNotFoundException
parse\Parse.java:    File[] arrayOfFile = getKeyValueCacheDir().listFiles();
parse\Parse.java:    if (arrayOfFile == null)
parse\Parse.java:      if (i < arrayOfFile.length);
parse\Parse.java:      arrayOfFile[i].delete();
parse\Parse.java:    File localFile = getKeyValueCacheFile(paramString);
parse\Parse.java:    if (localFile == null)
parse\Parse.java:    localFile.delete();
parse\Parse.java:  static File createKeyValueCacheFile(String paramString)
parse\Parse.java:    return new File(getKeyValueCacheDir(), str);
parse\Parse.java:      if (str.equals("File"))
parse\Parse.java:        localObject = new ParseFile(localJSONObject1.optString("name"), localJSONObject1.optString("url"));
parse\Parse.java:    else if (paramObject instanceof ParseFile)
parse\Parse.java:      ParseFile localParseFile = (ParseFile)paramObject;
parse\Parse.java:      ((JSONObject)localObject).put("__type", "File");
parse\Parse.java:      ((JSONObject)localObject).put("url", localParseFile.getUrl());
parse\Parse.java:      ((JSONObject)localObject).put("name", localParseFile.getName());
parse\Parse.java:  static long getKeyValueCacheAge(File paramFile)
parse\Parse.java:    String str = paramFile.getName();
parse\Parse.java:  static File getKeyValueCacheDir()
parse\Parse.java:      File localFile = new File(applicationContext.getCacheDir(), "ParseKeyValueCache");
parse\Parse.java:      if (!(localFile.isDirectory()))
parse\Parse.java:        boolean bool = localFile.mkdir();
parse\Parse.java:  static File getKeyValueCacheFile(String paramString)
parse\Parse.java:    File[] arrayOfFile = getKeyValueCacheDir().listFiles(new FilenameFilter(str)
parse\Parse.java:      public boolean accept(File paramFile, String paramString)
parse\Parse.java:    if (arrayOfFile.length == 0);
parse\Parse.java:    for (File localFile = null; ; localFile = arrayOfFile[0])
parse\Parse.java:      return localFile;
parse\Parse.java:  static File getParseDir()
parse\Parse.java:      File localFile = applicationContext.getDir("Parse", 0);
parse\Parse.java:      return localFile;
parse\Parse.java:    if ((paramObject instanceof JSONObject) || (paramObject instanceof JSONArray) || (paramObject instanceof String) || (paramObject instanceof Number) || (paramObject instanceof Boolean) || (paramObject == JSONObject.NULL) || (paramObject instanceof ParseObject) || (paramObject instanceof ParseACL) || (paramObject instanceof ParseFile) || (paramObject instanceof ParseGeoPoint) || (paramObject instanceof Date) || (paramObject instanceof byte[]) || (paramObject instanceof List) || (paramObject instanceof Map) || (paramObject instanceof ParseRelation));
parse\Parse.java:    File localFile = getKeyValueCacheFile(paramString);
parse\Parse.java:    if (localFile == null);
parse\Parse.java:      boolean bool = getKeyValueCacheAge(localFile) < l;
parse\Parse.java:      localFile.setLastModified(localDate.getTime());
parse\Parse.java:        RandomAccessFile localRandomAccessFile = new RandomAccessFile(localFile, "r");
parse\Parse.java:        byte[] arrayOfByte = new byte[(int)localRandomAccessFile.length()];
parse\Parse.java:        localRandomAccessFile.readFully(arrayOfByte);
parse\Parse.java:        localRandomAccessFile.close();
parse\Parse.java:  static void recursiveDelete(File paramFile)
parse\Parse.java:      if (paramFile.isDirectory())
parse\Parse.java:        File[] arrayOfFile = paramFile.listFiles();
parse\Parse.java:        int i = arrayOfFile.length;
parse\Parse.java:          recursiveDelete(arrayOfFile[j]);
parse\Parse.java:      paramFile.delete();
parse\Parse.java:    File localFile1 = getKeyValueCacheFile(paramString1);
parse\Parse.java:    if (localFile1 != null)
parse\Parse.java:      localFile1.delete();
parse\Parse.java:    File localFile2 = createKeyValueCacheFile(paramString1);
parse\Parse.java:      FileOutputStream localFileOutputStream = new FileOutputStream(localFile2);
parse\Parse.java:      localFileOutputStream.write(paramString2.getBytes("UTF-8"));
parse\Parse.java:      localFileOutputStream.close();
parse\Parse.java:      label45: File[] arrayOfFile = getKeyValueCacheDir().listFiles();
parse\Parse.java:      int i = arrayOfFile.length;
parse\Parse.java:      int k = arrayOfFile.length;
parse\Parse.java:        File localFile4 = arrayOfFile[l];
parse\Parse.java:        j = (int)(j + localFile4.length());
parse\Parse.java:      if ((i > maxKeyValueCacheFiles) || (j > maxKeyValueCacheBytes))
parse\Parse.java:        Arrays.sort(arrayOfFile, new Comparator()
parse\Parse.java:          public int compare(File paramFile1, File paramFile2)
parse\Parse.java:            int i = Long.valueOf(paramFile1.lastModified()).compareTo(Long.valueOf(paramFile2.lastModified()));
parse\Parse.java:              i = paramFile1.getName().compareTo(paramFile2.getName());
parse\Parse.java:        int i1 = arrayOfFile.length;
parse\Parse.java:          File localFile3 = arrayOfFile[i2];
parse\Parse.java:          j = (int)(j - localFile3.length());
parse\Parse.java:          localFile3.delete();
parse\Parse.java:          if ((i > maxKeyValueCacheFiles) || (j > maxKeyValueCacheBytes))
parse\ParseCommandCache.java:import java.io.File;
parse\ParseCommandCache.java:  private File cachePath;
parse\ParseCommandCache.java:  private HashMap<File, ParseCommand> commandsInCache = new HashMap();
parse\ParseCommandCache.java:    this.cachePath = new File(Parse.getParseDir(), "CommandCache");
parse\ParseCommandCache.java:  private void removeFile(File paramFile)
parse\ParseCommandCache.java:      File[] arrayOfFile = this.cachePath.listFiles();
parse\ParseCommandCache.java:      if (arrayOfFile == null)
parse\ParseCommandCache.java:      int i = arrayOfFile.length;
parse\ParseCommandCache.java:        removeFile(arrayOfFile[j]);
parse\ParseFile.java:public class ParseFile
parse\ParseFile.java:  private ParseFileState previousState;
parse\ParseFile.java:  private ParseFileState state;
parse\ParseFile.java:  ParseFile(String paramString1, String paramString2)
parse\ParseFile.java:    setState(ParseFileState.AWAITING_FETCH);
parse\ParseFile.java:  public ParseFile(String paramString, byte[] paramArrayOfByte)
parse\ParseFile.java:    if (paramArrayOfByte.length > Parse.maxParseFileSize)
parse\ParseFile.java:      arrayOfObject[0] = Integer.valueOf(Parse.maxParseFileSize);
parse\ParseFile.java:      throw new IllegalArgumentException(String.format("ParseFile must be less than %i bytes", arrayOfObject));
parse\ParseFile.java:    setState(ParseFileState.DIRTY);
parse\ParseFile.java:  public ParseFile(byte[] paramArrayOfByte)
parse\ParseFile.java:    if (paramArrayOfByte.length > Parse.maxParseFileSize)
parse\ParseFile.java:      arrayOfObject[0] = Integer.valueOf(Parse.maxParseFileSize);
parse\ParseFile.java:      throw new IllegalArgumentException(String.format("ParseFile must be less than %i bytes", arrayOfObject));
parse\ParseFile.java:    setState(ParseFileState.DIRTY);
parse\ParseFile.java:  private ParseCommand constructFileUploadCommand()
parse\ParseFile.java:  private void handleFileUploadResult(JSONObject paramJSONObject, ProgressCallback paramProgressCallback)
parse\ParseFile.java:    if (this.state != ParseFileState.SAVING);
parse\ParseFile.java:        prepareFileUploadPost(paramJSONObject, paramProgressCallback);
parse\ParseFile.java:      setState(ParseFileState.DATA_AVAILABLE);
parse\ParseFile.java:  private void prepareFileUploadPost(JSONObject paramJSONObject, ProgressCallback paramProgressCallback)
parse\ParseFile.java:    //   7: putfield 29	com/parse/ParseFile:name	Ljava/lang/String;
parse\ParseFile.java:    //   17: putfield 31	com/parse/ParseFile:url	Ljava/lang/String;
parse\ParseFile.java:    //   42: getfield 29	com/parse/ParseFile:name	Ljava/lang/String;
parse\ParseFile.java:    //   62: getfield 29	com/parse/ParseFile:name	Ljava/lang/String;
parse\ParseFile.java:    //   67: getfield 29	com/parse/ParseFile:name	Ljava/lang/String;
parse\ParseFile.java:    //   236: getfield 79	com/parse/ParseFile:data	[B
parse\ParseFile.java:    //   263: putfield 37	com/parse/ParseFile:fileUploadPost	Lorg/apache/http/client/methods/HttpPost;
parse\ParseFile.java:    //   267: getfield 37	com/parse/ParseFile:fileUploadPost	Lorg/apache/http/client/methods/HttpPost;
parse\ParseFile.java:      if (this.state == ParseFileState.DIRTY);
parse\ParseFile.java:      setState(ParseFileState.SAVING);
parse\ParseFile.java:        handleFileUploadResult((JSONObject)constructFileUploadCommand().perform(), paramProgressCallback);
parse\ParseFile.java:  private void setState(ParseFileState paramParseFileState)
parse\ParseFile.java:      if ((paramParseFileState != ParseFileState.SAVING) && (paramParseFileState != ParseFileState.FETCHING))
parse\ParseFile.java:      if (this.state != paramParseFileState)
parse\ParseFile.java:        this.state = paramParseFileState;
parse\ParseFile.java:    //   3: getfield 111	com/parse/ParseFile:state	Lcom/parse/ParseFile$ParseFileState;
parse\ParseFile.java:    //   6: getstatic 114	com/parse/ParseFile$ParseFileState:SAVING	Lcom/parse/ParseFile$ParseFileState;
parse\ParseFile.java:    //   13: getfield 111	com/parse/ParseFile:state	Lcom/parse/ParseFile$ParseFileState;
parse\ParseFile.java:    //   16: getstatic 245	com/parse/ParseFile$ParseFileState:FETCHING	Lcom/parse/ParseFile$ParseFileState;
parse\ParseFile.java:        setState(ParseFileState.FETCHING);
parse\ParseFile.java:        setState(ParseFileState.DATA_AVAILABLE);
parse\ParseFile.java:        if (this.state != ParseFileState.FETCHING)
parse\ParseFile.java:      setState(ParseFileState.FETCHING);
parse\ParseFile.java:          Iterator localIterator = ParseFile.this.callbacks.iterator();
parse\ParseFile.java:          ParseFile.this.callbacks.clear();
parse\ParseFile.java:          return ParseFile.this.getData(false, this.val$progressCallback);
parse\ParseFile.java:    if ((this.state != ParseFileState.AWAITING_FETCH) && (this.state != ParseFileState.FETCHING));
parse\ParseFile.java:    if (this.state == ParseFileState.DIRTY);
parse\ParseFile.java:      if (this.state != ParseFileState.DIRTY)
parse\ParseFile.java:      setState(ParseFileState.SAVING);
parse\ParseFile.java:          ParseFile.this.save(false, this.val$progressCallback);
parse\ParseFile.java:  private static enum ParseFileState
parse\ParseFile.java:      AWAITING_FETCH = new ParseFileState("AWAITING_FETCH", 2);
parse\ParseFile.java:      FETCHING = new ParseFileState("FETCHING", 3);
parse\ParseFile.java:      DATA_AVAILABLE = new ParseFileState("DATA_AVAILABLE", 4);
parse\ParseFile.java:      ParseFileState[] arrayOfParseFileState = new ParseFileState[5];
parse\ParseFile.java:      arrayOfParseFileState[0] = DIRTY;
parse\ParseFile.java:      arrayOfParseFileState[1] = SAVING;
parse\ParseFile.java:      arrayOfParseFileState[2] = AWAITING_FETCH;
parse\ParseFile.java:      arrayOfParseFileState[3] = FETCHING;
parse\ParseFile.java:      arrayOfParseFileState[4] = DATA_AVAILABLE;
parse\ParseFile.java:      $VALUES = arrayOfParseFileState;
parse\ParseFile.java: * Qualified Name:     com.parse.ParseFile
parse\ParseInstallation.java:    //   27: new 96	java/io/File
parse\ParseInstallation.java:    //   31: invokestatic 100	com/parse/Parse:getParseDir	()Ljava/io/File;
parse\ParseInstallation.java:    //   36: invokespecial 103	java/io/File:<init>	(Ljava/io/File;Ljava/lang/String;)V
parse\ParseInstallation.java:    //   43: invokevirtual 107	java/io/File:exists	()Z
parse\ParseInstallation.java:    //   63: new 118	java/io/RandomAccessFile
parse\ParseInstallation.java:    //   70: invokespecial 121	java/io/RandomAccessFile:<init>	(Ljava/io/File;Ljava/lang/String;)V
parse\ParseInstallation.java:    //   79: invokevirtual 125	java/io/RandomAccessFile:writeBytes	(Ljava/lang/String;)V
parse\ParseInstallation.java:    //   84: invokevirtual 128	java/io/RandomAccessFile:close	()V
parse\ParseInstallation.java:    //   94: invokevirtual 128	java/io/RandomAccessFile:close	()V
parse\ParseInstallation.java:    //   112: new 118	java/io/RandomAccessFile
parse\ParseInstallation.java:    //   119: invokespecial 121	java/io/RandomAccessFile:<init>	(Ljava/io/File;Ljava/lang/String;)V
parse\ParseInstallation.java:    //   126: invokevirtual 136	java/io/RandomAccessFile:length	()J
parse\ParseInstallation.java:    //   138: invokevirtual 140	java/io/RandomAccessFile:readFully	([B)V
parse\ParseInstallation.java:    //   159: invokevirtual 128	java/io/RandomAccessFile:close	()V
parse\ParseInstallation.java:    //   189: invokevirtual 128	java/io/RandomAccessFile:close	()V
parse\ParseInstallation.java:    //   206: invokevirtual 128	java/io/RandomAccessFile:close	()V
parse\ParseObject.java:import java.io.File;
parse\ParseObject.java:  private static void collectDirtyChildren(Object paramObject, List<ParseObject> paramList, List<ParseFile> paramList1)
parse\ParseObject.java:  private static void collectDirtyChildren(Object paramObject, List<ParseObject> paramList, List<ParseFile> paramList1, IdentityHashMap<ParseObject, ParseObject> paramIdentityHashMap1, IdentityHashMap<ParseObject, ParseObject> paramIdentityHashMap2)
parse\ParseObject.java:      if (!(paramObject instanceof ParseFile))
parse\ParseObject.java:      ParseFile localParseFile = (ParseFile)paramObject;
parse\ParseObject.java:      if (localParseFile.getUrl() != null)
parse\ParseObject.java:      paramList1.add(localParseFile);
parse\ParseObject.java:      ((ParseFile)localIterator1.next()).save();
parse\ParseObject.java:      File localFile = new File(Parse.getParseDir(), paramString);
parse\ParseObject.java:      if (localFile != null)
parse\ParseObject.java:        localFile.delete();
parse\ParseObject.java:      JSONObject localJSONObject = getDiskObject(new File(Parse.getParseDir(), paramString));
parse\ParseObject.java:  static JSONObject getDiskObject(File paramFile)
parse\ParseObject.java:    //   4: invokevirtual 589	java/io/File:exists	()Z
parse\ParseObject.java:    //   19: new 591	java/io/RandomAccessFile
parse\ParseObject.java:    //   27: invokespecial 594	java/io/RandomAccessFile:<init>	(Ljava/io/File;Ljava/lang/String;)V
parse\ParseObject.java:    //   34: invokevirtual 597	java/io/RandomAccessFile:length	()J
parse\ParseObject.java:    //   46: invokevirtual 601	java/io/RandomAccessFile:readFully	([B)V
parse\ParseObject.java:    //   51: invokevirtual 604	java/io/RandomAccessFile:close	()V
parse\ParseObject.java:      saveDiskObject(new File(Parse.getParseDir(), paramString), paramJSONObject);
parse\ParseObject.java:  static void saveDiskObject(File paramFile, JSONObject paramJSONObject)
parse\ParseObject.java:    //   3: new 698	java/io/FileOutputStream
parse\ParseObject.java:    //   8: invokespecial 701	java/io/FileOutputStream:<init>	(Ljava/io/File;)V
parse\ParseObject.java:    //   23: invokevirtual 709	java/io/FileOutputStream:write	([B)V
parse\ParseObject.java:    //   27: invokevirtual 710	java/io/FileOutputStream:close	()V
parse\ParseObject.java:    if ((paramObject instanceof ParseFile) && (((ParseFile)paramObject).isDirty()))
parse\ParseObject.java:      throw new IllegalArgumentException("ParseFile must be saved before being set on a ParseObject.");
parse\ParseObject.java:    saveDiskObject(paramContext, paramString, toJSONObjectForDataFile());
parse\ParseObject.java:  JSONObject toJSONObjectForDataFile()
parse\ParseTestUtils.java:import java.io.File;
parse\ParseTestUtils.java:import java.io.FileOutputStream;
parse\ParseTestUtils.java:  public static void clearFiles()
parse\ParseTestUtils.java:  static File getParseDir(Context paramContext)
parse\ParseTestUtils.java:  public static int numKeyValueCacheFiles()
parse\ParseTestUtils.java:    return Parse.getKeyValueCacheDir().listFiles().length;
parse\ParseTestUtils.java:  public static void recursiveDelete(File paramFile)
parse\ParseTestUtils.java:    if (!(paramFile.exists()));
parse\ParseTestUtils.java:      if (paramFile.isDirectory())
parse\ParseTestUtils.java:        File[] arrayOfFile = paramFile.listFiles();
parse\ParseTestUtils.java:        int i = arrayOfFile.length;
parse\ParseTestUtils.java:          recursiveDelete(arrayOfFile[j]);
parse\ParseTestUtils.java:      paramFile.delete();
parse\ParseTestUtils.java:    File localFile = new File(getParseDir(paramContext), paramString2);
parse\ParseTestUtils.java:      FileOutputStream localFileOutputStream = new FileOutputStream(localFile);
parse\ParseTestUtils.java:      localFileOutputStream.write(paramString1.getBytes("UTF-8"));
parse\ParseTestUtils.java:      localFileOutputStream.close();
parse\ParseTestUtils.java:  public static void setMaxKeyValueCacheFiles(int paramInt)
parse\ParseTestUtils.java:    Parse.maxKeyValueCacheFiles = paramInt;
parse\ParseTestUtils.java:    clearFiles();
parse\ParseUser.java:import java.io.File;
parse\ParseUser.java:    new File(Parse.getParseDir(), "currentUser").delete();
parse\ParseUser.java:  JSONObject toJSONObjectForDataFile()
parse\ParseUser.java:    //   1: invokespecial 598	com/parse/ParseObject:toJSONObjectForDataFile	()Lorg/json/JSONObject;
revmob\android\FileCache.java:import java.io.File;
revmob\android\FileCache.java:import java.io.FileNotFoundException;
revmob\android\FileCache.java:import java.io.FileOutputStream;
revmob\android\FileCache.java:public class FileCache
revmob\android\FileCache.java:  private File cacheDir;
revmob\android\FileCache.java:  public FileCache(Context paramContext)
revmob\android\FileCache.java:    for (this.cacheDir = new File(Environment.getExternalStorageDirectory(), "RevMob"); ; this.cacheDir = paramContext.getCacheDir())
revmob\android\FileCache.java:  public File getFile(String paramString)
revmob\android\FileCache.java:    return new File(this.cacheDir, paramString);
revmob\android\FileCache.java:  public void write(File paramFile, InputStream paramInputStream)
revmob\android\FileCache.java:      FileOutputStream localFileOutputStream = new FileOutputStream(paramFile);
revmob\android\FileCache.java:      copyStream(paramInputStream, localFileOutputStream);
revmob\android\FileCache.java:      localFileOutputStream.close();
revmob\android\FileCache.java:    catch (FileNotFoundException localFileNotFoundException)
revmob\android\FileCache.java: * Qualified Name:     com.revmob.android.FileCache
