package com.pad.android.xappad;

import android.app.NotificationManager;
import android.content.BroadcastReceiver;

public class AdReminderNotification extends BroadcastReceiver
{
  private NotificationManager a;

  // ERROR //
  public void onReceive(android.content.Context paramContext, android.content.Intent paramIntent)
  {
    // Byte code:
    //   0: aload_2
    //   1: invokevirtual 20	android/content/Intent:getExtras	()Landroid/os/Bundle;
    //   4: astore_3
    //   5: aload_3
    //   6: ldc 22
    //   8: invokevirtual 28	android/os/Bundle:getString	(Ljava/lang/String;)Ljava/lang/String;
    //   11: astore 4
    //   13: ldc 30
    //   15: new 32	java/lang/StringBuilder
    //   18: dup
    //   19: ldc 34
    //   21: invokespecial 37	java/lang/StringBuilder:<init>	(Ljava/lang/String;)V
    //   24: aload 4
    //   26: invokevirtual 41	java/lang/StringBuilder:append	(Ljava/lang/String;)Ljava/lang/StringBuilder;
    //   29: invokevirtual 45	java/lang/StringBuilder:toString	()Ljava/lang/String;
    //   32: invokestatic 51	com/pad/android/util/AdLog:i	(Ljava/lang/String;Ljava/lang/String;)V
    //   35: ldc 30
    //   37: new 32	java/lang/StringBuilder
    //   40: dup
    //   41: ldc 53
    //   43: invokespecial 37	java/lang/StringBuilder:<init>	(Ljava/lang/String;)V
    //   46: aload_3
    //   47: ldc 55
    //   49: invokevirtual 28	android/os/Bundle:getString	(Ljava/lang/String;)Ljava/lang/String;
    //   52: invokevirtual 41	java/lang/StringBuilder:append	(Ljava/lang/String;)Ljava/lang/StringBuilder;
    //   55: invokevirtual 45	java/lang/StringBuilder:toString	()Ljava/lang/String;
    //   58: invokestatic 51	com/pad/android/util/AdLog:i	(Ljava/lang/String;Ljava/lang/String;)V
    //   61: aload_3
    //   62: ldc 55
    //   64: invokevirtual 28	android/os/Bundle:getString	(Ljava/lang/String;)Ljava/lang/String;
    //   67: astore 5
    //   69: aload 5
    //   71: ldc 57
    //   73: invokevirtual 63	java/lang/String:equals	(Ljava/lang/Object;)Z
    //   76: ifeq +27 -> 103
    //   79: aload_0
    //   80: aload_1
    //   81: ldc 65
    //   83: invokevirtual 71	android/content/Context:getSystemService	(Ljava/lang/String;)Ljava/lang/Object;
    //   86: checkcast 73	android/app/NotificationManager
    //   89: putfield 75	com/pad/android/xappad/AdReminderNotification:a	Landroid/app/NotificationManager;
    //   92: aload_0
    //   93: getfield 75	com/pad/android/xappad/AdReminderNotification:a	Landroid/app/NotificationManager;
    //   96: sipush 1002
    //   99: invokevirtual 78	android/app/NotificationManager:cancel	(I)V
    //   102: return
    //   103: aload 5
    //   105: ldc 80
    //   107: invokevirtual 63	java/lang/String:equals	(Ljava/lang/Object;)Z
    //   110: ifeq -8 -> 102
    //   113: ldc 30
    //   115: new 32	java/lang/StringBuilder
    //   118: dup
    //   119: ldc 82
    //   121: invokespecial 37	java/lang/StringBuilder:<init>	(Ljava/lang/String;)V
    //   124: aload 4
    //   126: invokevirtual 41	java/lang/StringBuilder:append	(Ljava/lang/String;)Ljava/lang/StringBuilder;
    //   129: invokevirtual 45	java/lang/StringBuilder:toString	()Ljava/lang/String;
    //   132: invokestatic 51	com/pad/android/util/AdLog:i	(Ljava/lang/String;Ljava/lang/String;)V
    //   135: aload_0
    //   136: aload_1
    //   137: ldc 65
    //   139: invokevirtual 71	android/content/Context:getSystemService	(Ljava/lang/String;)Ljava/lang/Object;
    //   142: checkcast 73	android/app/NotificationManager
    //   145: putfield 75	com/pad/android/xappad/AdReminderNotification:a	Landroid/app/NotificationManager;
    //   148: iconst_5
    //   149: newarray int
    //   151: dup
    //   152: iconst_0
    //   153: ldc 83
    //   155: iastore
    //   156: dup
    //   157: iconst_1
    //   158: ldc 84
    //   160: iastore
    //   161: dup
    //   162: iconst_2
    //   163: ldc 85
    //   165: iastore
    //   166: dup
    //   167: iconst_3
    //   168: ldc 86
    //   170: iastore
    //   171: dup
    //   172: iconst_4
    //   173: ldc 87
    //   175: iastore
    //   176: astore 6
    //   178: ldc 89
    //   180: astore 7
    //   182: ldc 30
    //   184: ldc 91
    //   186: invokestatic 51	com/pad/android/util/AdLog:i	(Ljava/lang/String;Ljava/lang/String;)V
    //   189: aload_3
    //   190: ldc 93
    //   192: invokevirtual 28	android/os/Bundle:getString	(Ljava/lang/String;)Ljava/lang/String;
    //   195: invokestatic 99	java/lang/Integer:valueOf	(Ljava/lang/String;)Ljava/lang/Integer;
    //   198: invokevirtual 103	java/lang/Integer:intValue	()I
    //   201: istore 15
    //   203: iload 15
    //   205: istore 9
    //   207: aload_3
    //   208: ldc 105
    //   210: invokevirtual 28	android/os/Bundle:getString	(Ljava/lang/String;)Ljava/lang/String;
    //   213: astore 7
    //   215: aload_3
    //   216: ldc 107
    //   218: invokevirtual 28	android/os/Bundle:getString	(Ljava/lang/String;)Ljava/lang/String;
    //   221: astore 16
    //   223: ldc 30
    //   225: ldc 109
    //   227: invokestatic 112	com/pad/android/util/AdLog:e	(Ljava/lang/String;Ljava/lang/String;)V
    //   230: new 114	android/app/Notification
    //   233: dup
    //   234: aload 6
    //   236: iload 9
    //   238: iaload
    //   239: aload 7
    //   241: invokestatic 120	java/lang/System:currentTimeMillis	()J
    //   244: invokespecial 123	android/app/Notification:<init>	(ILjava/lang/CharSequence;J)V
    //   247: astore 17
    //   249: aload 17
    //   251: bipush 16
    //   253: aload 17
    //   255: getfield 127	android/app/Notification:flags	I
    //   258: ior
    //   259: putfield 127	android/app/Notification:flags	I
    //   262: aload 17
    //   264: aload_1
    //   265: aload 7
    //   267: aload 16
    //   269: aload_1
    //   270: iconst_0
    //   271: new 16	android/content/Intent
    //   274: dup
    //   275: invokespecial 128	android/content/Intent:<init>	()V
    //   278: iconst_0
    //   279: invokestatic 134	android/app/PendingIntent:getActivity	(Landroid/content/Context;ILandroid/content/Intent;I)Landroid/app/PendingIntent;
    //   282: invokevirtual 138	android/app/Notification:setLatestEventInfo	(Landroid/content/Context;Ljava/lang/CharSequence;Ljava/lang/CharSequence;Landroid/app/PendingIntent;)V
    //   285: ldc 30
    //   287: ldc 140
    //   289: invokestatic 112	com/pad/android/util/AdLog:e	(Ljava/lang/String;Ljava/lang/String;)V
    //   292: aload_1
    //   293: invokestatic 146	com/pad/android/xappad/AdWakeLock:acquire	(Landroid/content/Context;)V
    //   296: aload_0
    //   297: getfield 75	com/pad/android/xappad/AdReminderNotification:a	Landroid/app/NotificationManager;
    //   300: sipush 1002
    //   303: aload 17
    //   305: invokevirtual 150	android/app/NotificationManager:notify	(ILandroid/app/Notification;)V
    //   308: invokestatic 153	com/pad/android/xappad/AdWakeLock:release	()V
    //   311: return
    //   312: astore 18
    //   314: ldc 30
    //   316: aload 18
    //   318: invokestatic 157	com/pad/android/util/AdLog:printStackTrace	(Ljava/lang/String;Ljava/lang/Exception;)V
    //   321: ldc 30
    //   323: new 32	java/lang/StringBuilder
    //   326: dup
    //   327: ldc 159
    //   329: invokespecial 37	java/lang/StringBuilder:<init>	(Ljava/lang/String;)V
    //   332: aload 18
    //   334: invokevirtual 162	java/lang/Exception:getMessage	()Ljava/lang/String;
    //   337: invokevirtual 41	java/lang/StringBuilder:append	(Ljava/lang/String;)Ljava/lang/StringBuilder;
    //   340: invokevirtual 45	java/lang/StringBuilder:toString	()Ljava/lang/String;
    //   343: invokestatic 112	com/pad/android/util/AdLog:e	(Ljava/lang/String;Ljava/lang/String;)V
    //   346: return
    //   347: astore 12
    //   349: iconst_0
    //   350: istore 9
    //   352: ldc 30
    //   354: new 32	java/lang/StringBuilder
    //   357: dup
    //   358: ldc 164
    //   360: invokespecial 37	java/lang/StringBuilder:<init>	(Ljava/lang/String;)V
    //   363: aload 12
    //   365: invokevirtual 162	java/lang/Exception:getMessage	()Ljava/lang/String;
    //   368: invokevirtual 41	java/lang/StringBuilder:append	(Ljava/lang/String;)Ljava/lang/StringBuilder;
    //   371: invokevirtual 45	java/lang/StringBuilder:toString	()Ljava/lang/String;
    //   374: invokestatic 112	com/pad/android/util/AdLog:e	(Ljava/lang/String;Ljava/lang/String;)V
    //   377: ldc 30
    //   379: ldc 109
    //   381: invokestatic 112	com/pad/android/util/AdLog:e	(Ljava/lang/String;Ljava/lang/String;)V
    //   384: new 114	android/app/Notification
    //   387: dup
    //   388: aload 6
    //   390: iconst_0
    //   391: iaload
    //   392: aload 7
    //   394: invokestatic 120	java/lang/System:currentTimeMillis	()J
    //   397: invokespecial 123	android/app/Notification:<init>	(ILjava/lang/CharSequence;J)V
    //   400: astore 13
    //   402: aload 13
    //   404: bipush 16
    //   406: aload 13
    //   408: getfield 127	android/app/Notification:flags	I
    //   411: ior
    //   412: putfield 127	android/app/Notification:flags	I
    //   415: aload 13
    //   417: aload_1
    //   418: aload 7
    //   420: ldc 89
    //   422: aload_1
    //   423: iconst_0
    //   424: new 16	android/content/Intent
    //   427: dup
    //   428: invokespecial 128	android/content/Intent:<init>	()V
    //   431: iconst_0
    //   432: invokestatic 134	android/app/PendingIntent:getActivity	(Landroid/content/Context;ILandroid/content/Intent;I)Landroid/app/PendingIntent;
    //   435: invokevirtual 138	android/app/Notification:setLatestEventInfo	(Landroid/content/Context;Ljava/lang/CharSequence;Ljava/lang/CharSequence;Landroid/app/PendingIntent;)V
    //   438: ldc 30
    //   440: ldc 140
    //   442: invokestatic 112	com/pad/android/util/AdLog:e	(Ljava/lang/String;Ljava/lang/String;)V
    //   445: aload_1
    //   446: invokestatic 146	com/pad/android/xappad/AdWakeLock:acquire	(Landroid/content/Context;)V
    //   449: aload_0
    //   450: getfield 75	com/pad/android/xappad/AdReminderNotification:a	Landroid/app/NotificationManager;
    //   453: sipush 1002
    //   456: aload 13
    //   458: invokevirtual 150	android/app/NotificationManager:notify	(ILandroid/app/Notification;)V
    //   461: invokestatic 153	com/pad/android/xappad/AdWakeLock:release	()V
    //   464: return
    //   465: astore 14
    //   467: ldc 30
    //   469: aload 14
    //   471: invokestatic 157	com/pad/android/util/AdLog:printStackTrace	(Ljava/lang/String;Ljava/lang/Exception;)V
    //   474: ldc 30
    //   476: new 32	java/lang/StringBuilder
    //   479: dup
    //   480: ldc 159
    //   482: invokespecial 37	java/lang/StringBuilder:<init>	(Ljava/lang/String;)V
    //   485: aload 14
    //   487: invokevirtual 162	java/lang/Exception:getMessage	()Ljava/lang/String;
    //   490: invokevirtual 41	java/lang/StringBuilder:append	(Ljava/lang/String;)Ljava/lang/StringBuilder;
    //   493: invokevirtual 45	java/lang/StringBuilder:toString	()Ljava/lang/String;
    //   496: invokestatic 112	com/pad/android/util/AdLog:e	(Ljava/lang/String;Ljava/lang/String;)V
    //   499: return
    //   500: astore 8
    //   502: iconst_0
    //   503: istore 9
    //   505: ldc 30
    //   507: ldc 109
    //   509: invokestatic 112	com/pad/android/util/AdLog:e	(Ljava/lang/String;Ljava/lang/String;)V
    //   512: new 114	android/app/Notification
    //   515: dup
    //   516: aload 6
    //   518: iload 9
    //   520: iaload
    //   521: aload 7
    //   523: invokestatic 120	java/lang/System:currentTimeMillis	()J
    //   526: invokespecial 123	android/app/Notification:<init>	(ILjava/lang/CharSequence;J)V
    //   529: astore 10
    //   531: aload 10
    //   533: bipush 16
    //   535: aload 10
    //   537: getfield 127	android/app/Notification:flags	I
    //   540: ior
    //   541: putfield 127	android/app/Notification:flags	I
    //   544: aload 10
    //   546: aload_1
    //   547: aload 7
    //   549: ldc 89
    //   551: aload_1
    //   552: iconst_0
    //   553: new 16	android/content/Intent
    //   556: dup
    //   557: invokespecial 128	android/content/Intent:<init>	()V
    //   560: iconst_0
    //   561: invokestatic 134	android/app/PendingIntent:getActivity	(Landroid/content/Context;ILandroid/content/Intent;I)Landroid/app/PendingIntent;
    //   564: invokevirtual 138	android/app/Notification:setLatestEventInfo	(Landroid/content/Context;Ljava/lang/CharSequence;Ljava/lang/CharSequence;Landroid/app/PendingIntent;)V
    //   567: ldc 30
    //   569: ldc 140
    //   571: invokestatic 112	com/pad/android/util/AdLog:e	(Ljava/lang/String;Ljava/lang/String;)V
    //   574: aload_1
    //   575: invokestatic 146	com/pad/android/xappad/AdWakeLock:acquire	(Landroid/content/Context;)V
    //   578: aload_0
    //   579: getfield 75	com/pad/android/xappad/AdReminderNotification:a	Landroid/app/NotificationManager;
    //   582: sipush 1002
    //   585: aload 10
    //   587: invokevirtual 150	android/app/NotificationManager:notify	(ILandroid/app/Notification;)V
    //   590: invokestatic 153	com/pad/android/xappad/AdWakeLock:release	()V
    //   593: aload 8
    //   595: athrow
    //   596: astore 11
    //   598: ldc 30
    //   600: aload 11
    //   602: invokestatic 157	com/pad/android/util/AdLog:printStackTrace	(Ljava/lang/String;Ljava/lang/Exception;)V
    //   605: ldc 30
    //   607: new 32	java/lang/StringBuilder
    //   610: dup
    //   611: ldc 159
    //   613: invokespecial 37	java/lang/StringBuilder:<init>	(Ljava/lang/String;)V
    //   616: aload 11
    //   618: invokevirtual 162	java/lang/Exception:getMessage	()Ljava/lang/String;
    //   621: invokevirtual 41	java/lang/StringBuilder:append	(Ljava/lang/String;)Ljava/lang/StringBuilder;
    //   624: invokevirtual 45	java/lang/StringBuilder:toString	()Ljava/lang/String;
    //   627: invokestatic 112	com/pad/android/util/AdLog:e	(Ljava/lang/String;Ljava/lang/String;)V
    //   630: goto -37 -> 593
    //   633: astore 8
    //   635: goto -130 -> 505
    //   638: astore 12
    //   640: goto -288 -> 352
    //
    // Exception table:
    //   from	to	target	type
    //   285	311	312	java/lang/Exception
    //   182	203	347	java/lang/Exception
    //   438	464	465	java/lang/Exception
    //   182	203	500	finally
    //   567	593	596	java/lang/Exception
    //   207	223	633	finally
    //   352	377	633	finally
    //   207	223	638	java/lang/Exception
  }
}

/* Location:           C:\Users\Aitor\Desktop\ProyectoWifiHacker\mano.tavo.gps-3-v1.3-dex2jar\
 * Qualified Name:     com.pad.android.xappad.AdReminderNotification
 * JD-Core Version:    0.5.3
 */