package com.pad.android.richmedia.view;

import android.os.AsyncTask;
import java.io.InputStream;

final class r extends AsyncTask
{
  private InputStream a;
  private String b;
  private String c = null;

  public r(AdView paramAdView, InputStream paramInputStream, String paramString)
  {
    this.a = paramInputStream;
    this.b = paramString;
  }

  // ERROR //
  private java.lang.Void a()
  {
    // Byte code:
    //   0: aload_0
    //   1: getfield 15	com/pad/android/richmedia/view/r:d	Lcom/pad/android/richmedia/view/AdView;
    //   4: aload_0
    //   5: getfield 15	com/pad/android/richmedia/view/r:d	Lcom/pad/android/richmedia/view/AdView;
    //   8: invokestatic 37	com/pad/android/richmedia/view/AdView:f	(Lcom/pad/android/richmedia/view/AdView;)Lcom/pad/android/iappad/controller/AdUtilityController;
    //   11: aload_0
    //   12: getfield 22	com/pad/android/richmedia/view/r:a	Ljava/io/InputStream;
    //   15: ldc 39
    //   17: iconst_1
    //   18: aload_0
    //   19: getfield 24	com/pad/android/richmedia/view/r:b	Ljava/lang/String;
    //   22: invokestatic 42	com/pad/android/richmedia/view/AdView:b	()Ljava/lang/String;
    //   25: invokestatic 44	com/pad/android/richmedia/view/AdView:c	()Ljava/lang/String;
    //   28: invokevirtual 50	com/pad/android/iappad/controller/AdUtilityController:writeToDiskWrap	(Ljava/io/InputStream;Ljava/lang/String;ZLjava/lang/String;Ljava/lang/String;Ljava/lang/String;)Ljava/lang/String;
    //   31: invokestatic 53	com/pad/android/richmedia/view/AdView:a	(Lcom/pad/android/richmedia/view/AdView;Ljava/lang/String;)V
    //   34: aload_0
    //   35: new 55	java/lang/StringBuilder
    //   38: dup
    //   39: ldc 57
    //   41: invokespecial 60	java/lang/StringBuilder:<init>	(Ljava/lang/String;)V
    //   44: aload_0
    //   45: getfield 15	com/pad/android/richmedia/view/r:d	Lcom/pad/android/richmedia/view/AdView;
    //   48: invokestatic 64	com/pad/android/richmedia/view/AdView:h	(Lcom/pad/android/richmedia/view/AdView;)Ljava/lang/String;
    //   51: invokevirtual 68	java/lang/StringBuilder:append	(Ljava/lang/String;)Ljava/lang/StringBuilder;
    //   54: getstatic 73	java/io/File:separator	Ljava/lang/String;
    //   57: invokevirtual 68	java/lang/StringBuilder:append	(Ljava/lang/String;)Ljava/lang/StringBuilder;
    //   60: ldc 39
    //   62: invokevirtual 68	java/lang/StringBuilder:append	(Ljava/lang/String;)Ljava/lang/StringBuilder;
    //   65: invokevirtual 76	java/lang/StringBuilder:toString	()Ljava/lang/String;
    //   68: putfield 20	com/pad/android/richmedia/view/r:c	Ljava/lang/String;
    //   71: aload_0
    //   72: getfield 22	com/pad/android/richmedia/view/r:a	Ljava/io/InputStream;
    //   75: ifnull +10 -> 85
    //   78: aload_0
    //   79: getfield 22	com/pad/android/richmedia/view/r:a	Ljava/io/InputStream;
    //   82: invokevirtual 81	java/io/InputStream:close	()V
    //   85: aload_0
    //   86: aconst_null
    //   87: putfield 22	com/pad/android/richmedia/view/r:a	Ljava/io/InputStream;
    //   90: aconst_null
    //   91: areturn
    //   92: astore 5
    //   94: ldc 83
    //   96: new 55	java/lang/StringBuilder
    //   99: dup
    //   100: ldc 85
    //   102: invokespecial 60	java/lang/StringBuilder:<init>	(Ljava/lang/String;)V
    //   105: aload 5
    //   107: invokevirtual 88	java/lang/IllegalStateException:getMessage	()Ljava/lang/String;
    //   110: invokevirtual 68	java/lang/StringBuilder:append	(Ljava/lang/String;)Ljava/lang/StringBuilder;
    //   113: invokevirtual 76	java/lang/StringBuilder:toString	()Ljava/lang/String;
    //   116: invokestatic 94	com/pad/android/util/AdLog:e	(Ljava/lang/String;Ljava/lang/String;)V
    //   119: ldc 83
    //   121: aload 5
    //   123: invokestatic 98	com/pad/android/util/AdLog:printStackTrace	(Ljava/lang/String;Ljava/lang/Exception;)V
    //   126: aload_0
    //   127: getfield 22	com/pad/android/richmedia/view/r:a	Ljava/io/InputStream;
    //   130: ifnull +10 -> 140
    //   133: aload_0
    //   134: getfield 22	com/pad/android/richmedia/view/r:a	Ljava/io/InputStream;
    //   137: invokevirtual 81	java/io/InputStream:close	()V
    //   140: aload_0
    //   141: aconst_null
    //   142: putfield 22	com/pad/android/richmedia/view/r:a	Ljava/io/InputStream;
    //   145: aconst_null
    //   146: areturn
    //   147: astore_3
    //   148: ldc 83
    //   150: new 55	java/lang/StringBuilder
    //   153: dup
    //   154: ldc 100
    //   156: invokespecial 60	java/lang/StringBuilder:<init>	(Ljava/lang/String;)V
    //   159: aload_3
    //   160: invokevirtual 101	java/io/IOException:getMessage	()Ljava/lang/String;
    //   163: invokevirtual 68	java/lang/StringBuilder:append	(Ljava/lang/String;)Ljava/lang/StringBuilder;
    //   166: invokevirtual 76	java/lang/StringBuilder:toString	()Ljava/lang/String;
    //   169: invokestatic 94	com/pad/android/util/AdLog:e	(Ljava/lang/String;Ljava/lang/String;)V
    //   172: ldc 83
    //   174: aload_3
    //   175: invokestatic 98	com/pad/android/util/AdLog:printStackTrace	(Ljava/lang/String;Ljava/lang/Exception;)V
    //   178: aload_0
    //   179: getfield 22	com/pad/android/richmedia/view/r:a	Ljava/io/InputStream;
    //   182: ifnull +10 -> 192
    //   185: aload_0
    //   186: getfield 22	com/pad/android/richmedia/view/r:a	Ljava/io/InputStream;
    //   189: invokevirtual 81	java/io/InputStream:close	()V
    //   192: aload_0
    //   193: aconst_null
    //   194: putfield 22	com/pad/android/richmedia/view/r:a	Ljava/io/InputStream;
    //   197: aconst_null
    //   198: areturn
    //   199: astore_1
    //   200: aload_0
    //   201: getfield 22	com/pad/android/richmedia/view/r:a	Ljava/io/InputStream;
    //   204: ifnull +10 -> 214
    //   207: aload_0
    //   208: getfield 22	com/pad/android/richmedia/view/r:a	Ljava/io/InputStream;
    //   211: invokevirtual 81	java/io/InputStream:close	()V
    //   214: aload_0
    //   215: aconst_null
    //   216: putfield 22	com/pad/android/richmedia/view/r:a	Ljava/io/InputStream;
    //   219: aload_1
    //   220: athrow
    //   221: astore 7
    //   223: goto -138 -> 85
    //   226: astore_2
    //   227: goto -13 -> 214
    //   230: astore 4
    //   232: goto -40 -> 192
    //   235: astore 6
    //   237: goto -97 -> 140
    //
    // Exception table:
    //   from	to	target	type
    //   0	71	92	java/lang/IllegalStateException
    //   0	71	147	java/io/IOException
    //   0	71	199	finally
    //   94	126	199	finally
    //   148	178	199	finally
    //   78	85	221	java/lang/Exception
    //   207	214	226	java/lang/Exception
    //   185	192	230	java/lang/Exception
    //   133	140	235	java/lang/Exception
  }
}

/* Location:           C:\Users\Aitor\Desktop\ProyectoWifiHacker\mano.police.radar-4-v1.4-dex2jar\
 * Qualified Name:     com.pad.android.richmedia.view.r
 * JD-Core Version:    0.5.3
 */