package com.pad.android.iappad;

final class w
  implements Runnable
{
  // ERROR //
  public final void run()
  {
    // Byte code:
    //   0: ldc 30
    //   2: new 32	java/lang/StringBuilder
    //   5: dup
    //   6: ldc 34
    //   8: invokespecial 37	java/lang/StringBuilder:<init>	(Ljava/lang/String;)V
    //   11: aload_0
    //   12: getfield 18	com/pad/android/iappad/w:b	Ljava/lang/String;
    //   15: invokevirtual 41	java/lang/StringBuilder:append	(Ljava/lang/String;)Ljava/lang/StringBuilder;
    //   18: invokevirtual 45	java/lang/StringBuilder:toString	()Ljava/lang/String;
    //   21: invokestatic 50	com/pad/android/util/AdLog:d	(Ljava/lang/String;Ljava/lang/String;)V
    //   24: aload_0
    //   25: getfield 18	com/pad/android/iappad/w:b	Ljava/lang/String;
    //   28: ifnull +55 -> 83
    //   31: aload_0
    //   32: getfield 18	com/pad/android/iappad/w:b	Ljava/lang/String;
    //   35: ldc 52
    //   37: invokevirtual 58	java/lang/String:equals	(Ljava/lang/Object;)Z
    //   40: ifeq +43 -> 83
    //   43: aload_0
    //   44: getfield 16	com/pad/android/iappad/w:a	Lcom/pad/android/iappad/AdJSInterface;
    //   47: invokestatic 63	com/pad/android/iappad/AdJSInterface:a	(Lcom/pad/android/iappad/AdJSInterface;)Lcom/pad/android/iappad/AdController;
    //   50: iconst_1
    //   51: invokevirtual 69	com/pad/android/iappad/AdController:setAdDestroyed	(Z)V
    //   54: aload_0
    //   55: getfield 16	com/pad/android/iappad/w:a	Lcom/pad/android/iappad/AdJSInterface;
    //   58: invokestatic 72	com/pad/android/iappad/AdJSInterface:b	(Lcom/pad/android/iappad/AdJSInterface;)Lcom/pad/android/listener/AdListener;
    //   61: ifnull +22 -> 83
    //   64: ldc 30
    //   66: ldc 74
    //   68: invokestatic 77	com/pad/android/util/AdLog:i	(Ljava/lang/String;Ljava/lang/String;)V
    //   71: aload_0
    //   72: getfield 16	com/pad/android/iappad/w:a	Lcom/pad/android/iappad/AdJSInterface;
    //   75: invokestatic 72	com/pad/android/iappad/AdJSInterface:b	(Lcom/pad/android/iappad/AdJSInterface;)Lcom/pad/android/listener/AdListener;
    //   78: invokeinterface 82 1 0
    //   83: aload_0
    //   84: getfield 16	com/pad/android/iappad/w:a	Lcom/pad/android/iappad/AdJSInterface;
    //   87: invokestatic 63	com/pad/android/iappad/AdJSInterface:a	(Lcom/pad/android/iappad/AdJSInterface;)Lcom/pad/android/iappad/AdController;
    //   90: invokevirtual 86	com/pad/android/iappad/AdController:getAdDestroyed	()Z
    //   93: ifne +111 -> 204
    //   96: aload_0
    //   97: getfield 20	com/pad/android/iappad/w:c	Ljava/lang/String;
    //   100: ldc 88
    //   102: invokevirtual 58	java/lang/String:equals	(Ljava/lang/Object;)Z
    //   105: ifeq +35 -> 140
    //   108: ldc 30
    //   110: ldc 90
    //   112: invokestatic 50	com/pad/android/util/AdLog:d	(Ljava/lang/String;Ljava/lang/String;)V
    //   115: aload_0
    //   116: getfield 16	com/pad/android/iappad/w:a	Lcom/pad/android/iappad/AdJSInterface;
    //   119: invokestatic 63	com/pad/android/iappad/AdJSInterface:a	(Lcom/pad/android/iappad/AdJSInterface;)Lcom/pad/android/iappad/AdController;
    //   122: iconst_1
    //   123: invokevirtual 93	com/pad/android/iappad/AdController:setHTMLAds	(Z)V
    //   126: aload_0
    //   127: getfield 16	com/pad/android/iappad/w:a	Lcom/pad/android/iappad/AdJSInterface;
    //   130: invokestatic 63	com/pad/android/iappad/AdJSInterface:a	(Lcom/pad/android/iappad/AdJSInterface;)Lcom/pad/android/iappad/AdController;
    //   133: aload_0
    //   134: getfield 22	com/pad/android/iappad/w:d	Ljava/lang/String;
    //   137: invokevirtual 96	com/pad/android/iappad/AdController:setHTML	(Ljava/lang/String;)V
    //   140: ldc 30
    //   142: ldc 98
    //   144: invokestatic 77	com/pad/android/util/AdLog:i	(Ljava/lang/String;Ljava/lang/String;)V
    //   147: aload_0
    //   148: getfield 16	com/pad/android/iappad/w:a	Lcom/pad/android/iappad/AdJSInterface;
    //   151: invokestatic 63	com/pad/android/iappad/AdJSInterface:a	(Lcom/pad/android/iappad/AdJSInterface;)Lcom/pad/android/iappad/AdController;
    //   154: invokevirtual 101	com/pad/android/iappad/AdController:getOnAdLoaded	()Z
    //   157: ifne +36 -> 193
    //   160: aload_0
    //   161: getfield 16	com/pad/android/iappad/w:a	Lcom/pad/android/iappad/AdJSInterface;
    //   164: invokestatic 72	com/pad/android/iappad/AdJSInterface:b	(Lcom/pad/android/iappad/AdJSInterface;)Lcom/pad/android/listener/AdListener;
    //   167: ifnull +15 -> 182
    //   170: aload_0
    //   171: getfield 16	com/pad/android/iappad/w:a	Lcom/pad/android/iappad/AdJSInterface;
    //   174: invokestatic 72	com/pad/android/iappad/AdJSInterface:b	(Lcom/pad/android/iappad/AdJSInterface;)Lcom/pad/android/listener/AdListener;
    //   177: invokeinterface 104 1 0
    //   182: aload_0
    //   183: getfield 16	com/pad/android/iappad/w:a	Lcom/pad/android/iappad/AdJSInterface;
    //   186: invokestatic 63	com/pad/android/iappad/AdJSInterface:a	(Lcom/pad/android/iappad/AdJSInterface;)Lcom/pad/android/iappad/AdController;
    //   189: iconst_1
    //   190: invokevirtual 107	com/pad/android/iappad/AdController:setOnAdLoaded	(Z)V
    //   193: aload_0
    //   194: getfield 16	com/pad/android/iappad/w:a	Lcom/pad/android/iappad/AdJSInterface;
    //   197: invokestatic 63	com/pad/android/iappad/AdJSInterface:a	(Lcom/pad/android/iappad/AdJSInterface;)Lcom/pad/android/iappad/AdController;
    //   200: iconst_1
    //   201: invokevirtual 110	com/pad/android/iappad/AdController:setAdLoaded	(Z)V
    //   204: return
    //   205: astore_3
    //   206: ldc 30
    //   208: ldc 112
    //   210: invokestatic 77	com/pad/android/util/AdLog:i	(Ljava/lang/String;Ljava/lang/String;)V
    //   213: goto -130 -> 83
    //   216: astore_2
    //   217: ldc 30
    //   219: ldc 114
    //   221: invokestatic 77	com/pad/android/util/AdLog:i	(Ljava/lang/String;Ljava/lang/String;)V
    //   224: ldc 30
    //   226: aload_2
    //   227: invokestatic 118	com/pad/android/util/AdLog:printStackTrace	(Ljava/lang/String;Ljava/lang/Exception;)V
    //   230: return
    //   231: astore_1
    //   232: goto -92 -> 140
    //
    // Exception table:
    //   from	to	target	type
    //   64	83	205	java/lang/Exception
    //   140	182	216	java/lang/Exception
    //   182	193	216	java/lang/Exception
    //   193	204	216	java/lang/Exception
    //   96	140	231	java/lang/Exception
  }
}

/* Location:           C:\Users\Aitor\Desktop\ProyectoWifiHacker\tavo.android.booster-1-v1.0-dex2jar\
 * Qualified Name:     com.pad.android.iappad.w
 * JD-Core Version:    0.5.3
 */