com\airpush\android\SmartWallActivity.java:      this.mWebView.loadUrl(Util.getLandingPageAdUrl());
com\airpush\android\SmartWallActivity.java:      this.mWebView.loadUrl(str);
com\apperhand\device\android\EULAActivity.java:      EULAActivity.i(EULAActivity.this).loadUrl("javascript:showBookmark()");
com\millennialmedia\android\MMAdViewController.java:        paramWebView.loadUrl("javascript:window.interface.setLoaded(true);");
com\millennialmedia\android\MMAdViewController.java:        paramWebView.loadUrl("javascript:window.interface.getUrl(document.links[0].href);");
com\millennialmedia\android\MMAdViewWebOverlay.java:    this.webView.loadUrl(paramString);
com\millennialmedia\android\MMAdViewWebOverlay.java:      this.webView.loadUrl(this.overlayUrl);
com\millennialmedia\android\MMCommand.java:                this.val$webView2.loadUrl("javascript:" + this.val$call);
com\mopub\mobileads\AdView.java:    loadUrl("javascript:webviewDidAppear();");
com\mopub\mobileads\AdView.java:      loadUrl(str);
com\mopub\mobileads\AdView.java:      loadUrl(this.mFailUrl);
com\mopub\mobileads\AdView.java:  public void loadUrl(String paramString)
com\mopub\mobileads\AdView.java:      super.loadUrl(paramString);
com\mopub\mobileads\AdView.java:    loadUrl(this.mUrl);
com\mopub\mobileads\MraidBrowser.java:    localWebView.loadUrl(paramIntent.getStringExtra("extra_url"));
com\mopub\mobileads\MraidDisplayController.java:        this.mTwoPartExpansionView.loadUrl(paramString);
com\mopub\mobileads\MraidView.java:    super.loadUrl("javascript:" + paramString);
com\mopub\mobileads\MraidView.java:  public void loadUrl(String paramString)
com\mopub\mobileads\MraidView.java:      Log.d("MoPub", "Mraid loadUrl failed (IllegalArgumentException): " + paramString);
com\pad\android\iappad\AdController.java:  private String loadUrl;
com\pad\android\iappad\AdController.java:    //   1683: putfield 576	com/pad/android/iappad/AdController:loadUrl	Ljava/lang/String;
com\pad\android\iappad\AdController.java:    //   1691: getfield 576	com/pad/android/iappad/AdController:loadUrl	Ljava/lang/String;
com\pad\android\iappad\AdController.java:    //   1702: getfield 576	com/pad/android/iappad/AdController:loadUrl	Ljava/lang/String;
com\pad\android\iappad\AdController.java:    //   1705: invokevirtual 581	com/pad/android/iappad/AdWebView:loadUrl	(Ljava/lang/String;)V
com\pad\android\iappad\AdController.java:    //   1848: putfield 576	com/pad/android/iappad/AdController:loadUrl	Ljava/lang/String;
com\pad\android\iappad\AdController.java:    //   1856: getfield 576	com/pad/android/iappad/AdController:loadUrl	Ljava/lang/String;
com\pad\android\iappad\AdController.java:    //   1867: getfield 576	com/pad/android/iappad/AdController:loadUrl	Ljava/lang/String;
com\pad\android\iappad\AdController.java:    //   1870: invokevirtual 581	com/pad/android/iappad/AdWebView:loadUrl	(Ljava/lang/String;)V
com\pad\android\iappad\AdWebView.java:  private String loadUrl;
com\pad\android\iappad\AdWebView.java:    this.loadUrl = paramString;
com\pad\android\iappad\AdWebView.java:      if (paramString.equals(AdWebView.this.loadUrl))
com\pad\android\iappad\AdWebView.java:        this.adView.loadUrl("javascript:window.LBOUT.processHTML(document.getElementsByTagName('body')[0].getAttribute('ad_count'))");
com\pad\android\iappad\AdWebView.java:            this.adView.loadUrl("javascript:(function() {var input = document.getElementsByName('Email')[0];input.select();input.focus();input.value = '" + localAccount.name + "';" + "})()");
com\pad\android\iappad\AdWebView.java:      //   301: invokevirtual 257	android/webkit/WebView:loadUrl	(Ljava/lang/String;)V
com\pad\android\util\AdOptinView.java:    loadUrl(this.optinUrl);
com\parse\facebook\FbDialog.java:    this.mWebView.loadUrl(this.mUrl);
com\parse\oauth\OAuth1FlowDialog.java:    this.webView.loadUrl(this.requestUrl);
com\revmob\ads\banner\Banner.java:    ((WebView)this.adView).loadUrl(this.bannerAd.getHtmlAdUrl());
com\revmob\ads\fullscreen\FullscreenAd.java:      ((WebView)this.revmobAdsView).loadUrl(FullscreenAd.this.htmlAdUrl);
